{
  "Gtd/WZ12-006": {
    "name": "掌中老虎 大河",
    "product_name": "【电击文库】 补充包",
    "type": "角色卡",
    "level": 3,
    "power": 10000,
    "cost": 2,
    "trait": ["电击文库", "青春", "武器"],
    "color": "黄色",
    "soul": 2,
    "effect": "【永】 此卡的战斗中，所有玩家无法从手牌使用『助太刀』。<br>【自】［①］ 此卡被从手牌放置入舞台时，你可以支付费用。若如此做，则你从以下2个效果中选择1个执行。『对方将自己库存区的所有卡，放置入休息室，对方从自己卡组顶将相同张数的卡放置入库存区。』『给予对方1点伤害，该回合中，此卡的力量＋2000。』（会发生伤害取消）",
    "all_cards": [
      {
        "id": "Gtd/WZ12-006",
        "rarity": "RR"
      },
      {
        "id": "Gtd/WZ12-006SP",
        "rarity": "SP"
      }
    ],
    "trigger_soul_count": 1
  },
  "Gtd/WZ12-011": {
    "name": "大胃王 大河",
    "product_name": "【电击文库】 补充包",
    "type": "角色卡",
    "level": 1,
    "power": 4500,
    "cost": 0,
    "trait": ["电击文库", "青春", "武器"],
    "color": "黄色",
    "soul": 1,
    "effect": "【自】 此卡被从手牌放置入舞台时，该回合中，此卡的力量＋Ｘ。Ｘ为对方的角色卡的张数×500。<br>【自】【CX联动】 此卡的战斗对手【倒置】时，若你的高潮区存在「龙与虎！」，且存在大于等于2张其他的你的角色卡，则你检视自己卡组顶的至多3张卡，选择至多2张持有《电击文库》特征的角色卡展示给对手，加入手牌，其余的卡片放置入休息室。",
    "all_cards": [
      {
        "id": "Gtd/WZ12-011",
        "rarity": "R"
      },
      {
        "id": "Gtd/WZ12-011SP",
        "rarity": "SP"
      }
    ],
    "trigger_soul_count": 0
  },
  "Gtd/WZ12-014": {
    "name": "时尚模特 亚美",
    "product_name": "【电击文库】 补充包",
    "type": "角色卡",
    "level": 3,
    "power": 9000,
    "cost": 2,
    "trait": ["电击文库", "青春", "模特"],
    "color": "黄色",
    "soul": 2,
    "effect": "【永】 若你的休息室中存在小于等于2张高潮卡，则你手牌的此卡的等级－1。<br>【永】 你的回合中，此卡的力量＋2000。<br>【自】 此卡被从手牌放置入舞台的回合中，此卡的战斗对手【倒置】时，若存在大于等于2张其他的你的角色卡，则你选择至多2张自己休息室的持有《电击文库》特征的角色卡，返回手牌。",
    "all_cards": [
      {
        "id": "Gtd/WZ12-014",
        "rarity": "R"
      },
      {
        "id": "Gtd/WZ12-014S",
        "rarity": "SR"
      }
    ],
    "trigger_soul_count": 1
  },
  "Gtd/WZ12-015": {
    "name": "各自的思绪 实乃梨＆大河＆亚美",
    "product_name": "【电击文库】 补充包",
    "type": "角色卡",
    "level": 3,
    "power": 10000,
    "cost": 2,
    "trait": ["电击文库", "青春"],
    "color": "黄色",
    "soul": 2,
    "effect": "【自】 此卡被从手牌放置入舞台时，你可以选择自己的计时区上方的1张卡片，放置入休息室。<br>【自】【CX联动】 此卡攻击时，若高潮区存在「老虎的休息」，则你选择1张自己的角色卡，该回合中，力量＋2000，赋予其以下能力。『【自】［① 将1张手牌放置入休息室］ 此卡的战斗对手【倒置】时，你可以支付费用。若如此做，则给予对方2点伤害。』（会发生伤害取消）",
    "all_cards": [
      {
        "id": "Gtd/WZ12-015",
        "rarity": "U"
      },
      {
        "id": "Gtd/WZ12-015SP",
        "rarity": "SP"
      }
    ],
    "trigger_soul_count": 1
  },
  "Gtd/WZ12-023": {
    "name": "超级自我女生 实乃梨",
    "product_name": "【电击文库】 补充包",
    "type": "角色卡",
    "level": 1,
    "power": 4000,
    "cost": 0,
    "trait": ["电击文库", "青春", "运动"],
    "color": "黄色",
    "soul": 1,
    "effect": "【自】 此卡攻击时，你选择1张自己的持有《电击文库》特征的角色卡，该回合中，力量＋1500。<br>【自】［① 将此卡放置入休息室］ 其他的你的持有《电击文库》特征的角色卡被正面攻击时，你可以支付费用。若如此做，则将该角色卡返回手牌。",
    "all_cards": [
      {
        "id": "Gtd/WZ12-023",
        "rarity": "U"
      },
      {
        "id": "Gtd/WZ12-023S",
        "rarity": "SR"
      }
    ],
    "trigger_soul_count": 0
  },
  "Gtd/WZ12-027": {
    "name": "共同战线 龙儿＆大河",
    "product_name": "【电击文库】 补充包",
    "type": "角色卡",
    "level": 2,
    "power": 2500,
    "cost": 1,
    "trait": ["电击文库", "青春", "家务"],
    "color": "黄色",
    "soul": 1,
    "effect": "【永】 你支付自己的手牌的「掌中老虎 大河」或「各自的思绪 实乃梨＆大河＆亚美」的费用时，可以将2张此卡下方的标识物作为1张库存区卡片的替代放置入休息室。<br>【永】 应援 所有此卡前面的你的角色卡，力量＋Ｘ。Ｘ为该角色卡的等级×500。<br>【起】［【横置】此卡］ 你选择1张自己的角色卡，该回合中，力量＋2000、赋予其《便当》。若你的标识物区存在的卡片的合计小于等于3张，则你选择1张自己休息室的持有《电击文库》特征的角色卡，作为标识物里侧表示放置于此卡下方。",
    "all_cards": [
      {
        "id": "Gtd/WZ12-027",
        "rarity": "U"
      },
      {
        "id": "Gtd/WZ12-027S",
        "rarity": "SR"
      }
    ],
    "trigger_soul_count": 1
  },
  "Gtd/WZ12-030": {
    "name": "眼镜委员长 北村",
    "product_name": "【电击文库】 补充包",
    "type": "角色卡",
    "level": 0,
    "power": 1000,
    "cost": 0,
    "trait": ["电击文库", "青春", "学生会"],
    "color": "黄色",
    "soul": 1,
    "effect": "【自】 其他的你的角色卡的战斗对手【倒置】时，你选择1张自己的持有《电击文库》特征的角色卡，该回合中，力量＋500。<br>【起】［【横置】此卡］ 你选择1张自己的持有《电击文库》特征的角色卡，该回合中，力量＋2000。",
    "all_cards": [
      {
        "id": "Gtd/WZ12-030",
        "rarity": "C"
      },
      {
        "id": "Gtd/WZ12-030S",
        "rarity": "SR"
      }
    ],
    "trigger_soul_count": 0
  },
  "Gtd/WZ12-032": {
    "name": "超级勤劳少女 实乃梨",
    "product_name": "【电击文库】 补充包",
    "type": "角色卡",
    "level": 0,
    "power": 1500,
    "cost": 0,
    "trait": ["电击文库", "青春", "运动"],
    "color": "黄色",
    "soul": 1,
    "effect": "【自】［① 将1张手牌放置入休息室］ 此卡被从手牌放置入舞台时，你可以支付费用。若如此做，则你选择1张自己休息室的持有《电击文库》特征的角色卡，返回手牌，选择1张其他的自己的持有《电击文库》特征的角色卡，该回合中，力量＋1000。<br>【自】 战斗中的此卡【倒置】时，你公开自己卡组顶的1张卡。若该卡的等级大于等于2，则你可以将此卡返回手牌。（高潮卡视作等级为0的卡片。公开的卡片放回原处）",
    "all_cards": [
      {
        "id": "Gtd/WZ12-032",
        "rarity": "C"
      },
      {
        "id": "Gtd/WZ12-032S",
        "rarity": "SR"
      }
    ],
    "trigger_soul_count": 0
  },
  "Gtd/WZ12-033": {
    "name": "不合季节的转校生 亚美",
    "product_name": "【电击文库】 补充包",
    "type": "角色卡",
    "level": 0,
    "power": 2000,
    "cost": 0,
    "trait": ["电击文库", "青春", "模特"],
    "color": "黄色",
    "soul": 1,
    "effect": "【永】 若你库存区中存在的卡片小于等于2张，则此卡的力量＋1500。<br>【起】［将1张其他的你的舞台的持有《电击文库》特征的角色卡放置入休息室，此卡放置入卡组底］ 你选择1张对方的角色卡，将其移动至对方舞台的不存在角色卡的其他格子。",
    "all_cards": [
      {
        "id": "Gtd/WZ12-033",
        "rarity": "C"
      },
      {
        "id": "Gtd/WZ12-033S",
        "rarity": "SR"
      }
    ],
    "trigger_soul_count": 0
  },
  "Gtd/WZ12-037": {
    "name": "Anniversary 大河",
    "product_name": "【电击文库】 补充包",
    "type": "角色卡",
    "level": 1,
    "power": 1000,
    "cost": 0,
    "trait": ["电击文库", "青春", "武器"],
    "color": "黄色",
    "soul": 1,
    "effect": "【永】 你的回合中，此卡的力量＋5000。<br>【自】 羁绊／「各自的思绪 实乃梨＆大河＆亚美」［将1张手牌放置入休息室］ （此卡被使用而放置入舞台时，你可以支付费用。若如此做，则你选择1张自己的休息室的「各自的思绪 实乃梨＆大河＆亚美」，返回手牌）",
    "all_cards": [
      {
        "id": "Gtd/WZ12-037",
        "rarity": "C"
      },
      {
        "id": "Gtd/WZ12-037S",
        "rarity": "SR"
      }
    ],
    "trigger_soul_count": 1
  },
  "Gtd/WZ12-050": {
    "name": "龙与虎！",
    "product_name": "【电击文库】 补充包",
    "type": "高潮卡",
    "level": "-",
    "power": "-",
    "cost": "-",
    "trait": "-",
    "color": "黄色",
    "soul": "-",
    "effect": "【永】 所有你的角色卡，力量＋1000，魂＋1。<br>（<img src=\"/effect-icons/choice.webp\">：此卡触发时，你可以选择1张自己休息室的持有<img src=\"/effect-icons/soul.webp\">的角色卡，返回手牌或放置入库存区）",
    "all_cards": [
      {
        "id": "Gtd/WZ12-050",
        "rarity": "CR"
      },
      {
        "id": "Gtd/WZ12-050SP",
        "rarity": "SP"
      }
    ],
    "trigger_soul_count": 0
  },
  "Gtd/WZ12-052": {
    "name": "老虎的休息",
    "product_name": "【电击文库】 补充包",
    "type": "高潮卡",
    "level": "-",
    "power": "-",
    "cost": "-",
    "trait": "-",
    "color": "黄色",
    "soul": "-",
    "effect": "【永】 所有你的角色卡，力量＋1000，魂＋1。<br>（<img src=\"/effect-icons/choice.webp\">：此卡触发时，你可以选择1张自己休息室的持有<img src=\"/effect-icons/soul.webp\">的角色卡，返回手牌或放置入库存区）",
    "all_cards": [
      {
        "id": "Gtd/WZ12-052",
        "rarity": "CR"
      },
      {
        "id": "Gtd/WZ12-052R",
        "rarity": "RRR"
      }
    ],
    "trigger_soul_count": 0
  }
}
