{
  "DC/WE08-01": {
    "name": "完全無欠なお姉ちゃん 音姫",
    "product_name": "D.C. D.C.II プラスコミュニケーション",
    "type": "角色卡",
    "level": 0,
    "power": 500,
    "cost": 0,
    "trait": ["魔法", "生徒会"],
    "color": "黄色",
    "soul": 1,
    "effect": "【永】这张卡不会被对手的效果选择。<br/>【永】应援 你这张卡前的全部角色，战斗力+500。",
    "all_cards": [
      {
        "id": "DC/WE08-01",
        "rarity": "R"
      }
    ],
    "trigger_soul_count": 0
  },
  "DC/WE08-02": {
    "name": "帰って来たカノジョ まひる",
    "product_name": "D.C. D.C.II プラスコミュニケーション",
    "type": "角色卡",
    "level": 1,
    "power": 4500,
    "cost": 0,
    "trait": ["たとえ話"],
    "color": "黄色",
    "soul": 1,
    "effect": "【自】[(1) 手牌中1张「へーよーぶらざー」放置到休息室] 这张卡攻击时，你可以支付费用。支付了的话，你从自己的卡组找至多2张《たとえ話》或《委員長》的角色卡展示给对手后加入手牌。卡组洗切。<br/>【自】[(1)] 这张卡从舞台放置到休息室时，你可以支付费用。支付了的话，这张卡思出。",
    "all_cards": [
      {
        "id": "DC/WE08-02",
        "rarity": "R"
      }
    ],
    "trigger_soul_count": 0
  },
  "DC/WE08-03": {
    "name": "世界が忘れた少女 アイシア",
    "product_name": "D.C. D.C.II プラスコミュニケーション",
    "type": "角色卡",
    "level": 0,
    "power": 2000,
    "cost": 0,
    "trait": ["魔法", "オモチャ"],
    "color": "黄色",
    "soul": 1,
    "effect": "【自】这张卡从手牌放置到舞台时，那个回合中，这张卡的战斗力+1500。<br/>【自】这张卡从舞台放置到思出区时，这张卡放置到库存区。",
    "all_cards": [
      {
        "id": "DC/WE08-03",
        "rarity": "C"
      }
    ],
    "trigger_soul_count": 0
  },
  "DC/WE08-04": {
    "name": "噂の転入生 さくら",
    "product_name": "D.C. D.C.II プラスコミュニケーション",
    "type": "角色卡",
    "level": 1,
    "power": 5000,
    "cost": 0,
    "trait": ["魔法", "お菓子"],
    "color": "黄色",
    "soul": 1,
    "effect": "【自】这张卡攻击时，你公开自己卡组顶1张卡。那张卡是《魔法》的角色卡的话，你选择自己的1个角色，那个回合中，战斗力+1000。（公开的卡放回原处）",
    "all_cards": [
      {
        "id": "DC/WE08-04",
        "rarity": "C"
      }
    ],
    "trigger_soul_count": 0
  },
  "DC/WE08-05": {
    "name": "へーよーぶらざー",
    "product_name": "D.C. D.C.II プラスコミュニケーション",
    "type": "高潮卡",
    "level": "-",
    "power": "-",
    "cost": "-",
    "trait": "-",
    "color": "黄色",
    "soul": "-",
    "effect": "【自】这张卡从手牌放置到高潮区时，你抽1张卡，选择自己的1个角色，那个回合中，灵魂值+3。",
    "all_cards": [
      {
        "id": "DC/WE08-05",
        "rarity": "C"
      }
    ],
    "trigger_soul_count": 2
  },
  "DC/WE08-06": {
    "name": "聖歌隊のことり",
    "product_name": "D.C. D.C.II プラスコミュニケーション",
    "type": "角色卡",
    "level": 1,
    "power": 3000,
    "cost": 0,
    "trait": ["音楽", "魔法"],
    "color": "绿色",
    "soul": 1,
    "effect": "【永】你其他位于前列中央的角色，战斗力+1000。<br/>【自】[1张手牌放置到休息室] 你的「結婚式の歌姫」放置到高潮区时，你可以支付费用。支付了的话，你从自己的卡组找至多1张《音楽》的角色卡展示给对手后加入手牌。卡组洗切。",
    "all_cards": [
      {
        "id": "DC/WE08-06",
        "rarity": "R"
      }
    ],
    "trigger_soul_count": 0
  },
  "DC/WE08-07": {
    "name": "ちょっとだけ、おもいで 茜",
    "product_name": "D.C. D.C.II プラスコミュニケーション",
    "type": "角色卡",
    "level": 0,
    "power": 2500,
    "cost": 0,
    "trait": ["特徴なし"],
    "color": "绿色",
    "soul": 1,
    "effect": "【永】你其他没有特征的角色有2个以上的话，这张卡的战斗力+1000。",
    "all_cards": [
      {
        "id": "DC/WE08-07",
        "rarity": "C"
      }
    ],
    "trigger_soul_count": 0
  },
  "DC/WE08-08": {
    "name": "軽音楽部 小恋",
    "product_name": "D.C. D.C.II プラスコミュニケーション",
    "type": "角色卡",
    "level": 1,
    "power": 5500,
    "cost": 0,
    "trait": ["音楽", "ヘッドフォン"],
    "color": "绿色",
    "soul": 1,
    "effect": "",
    "all_cards": [
      {
        "id": "DC/WE08-08",
        "rarity": "C"
      }
    ],
    "trigger_soul_count": 0
  },
  "DC/WE08-09": {
    "name": "素直になれる勇気 ななか",
    "product_name": "D.C. D.C.II プラスコミュニケーション",
    "type": "角色卡",
    "level": 2,
    "power": 5000,
    "cost": 1,
    "trait": ["音楽", "魔法"],
    "color": "绿色",
    "soul": 1,
    "effect": "【永】你的费用在5张以上的话，你其他全部角色，等级+1，战斗力+500。<br/>【自】你的「夢じゃない」放置到高潮区时，你可以将自己卡组顶1张卡放置到库存区。",
    "all_cards": [
      {
        "id": "DC/WE08-09",
        "rarity": "C"
      }
    ],
    "trigger_soul_count": 1
  },
  "DC/WE08-10": {
    "name": "素直になれない妹 由夢",
    "product_name": "D.C. D.C.II プラスコミュニケーション",
    "type": "角色卡",
    "level": 2,
    "power": 8000,
    "cost": 1,
    "trait": ["魔法"],
    "color": "红色",
    "soul": 1,
    "effect": "【自】[(1)] 这张卡等级2以上的战斗对手倒置时，你可以支付费用。支付了的话，你从自己的休息室选择1张角色卡返回手牌。",
    "all_cards": [
      {
        "id": "DC/WE08-10",
        "rarity": "R"
      }
    ],
    "trigger_soul_count": 1
  },
  "DC/WE08-11": {
    "name": "風見学園の生徒 美夏",
    "product_name": "D.C. D.C.II プラスコミュニケーション",
    "type": "角色卡",
    "level": 3,
    "power": 10000,
    "cost": 2,
    "trait": ["メカ", "バナナ"],
    "color": "红色",
    "soul": 2,
    "effect": "【永】大活躍 （对手攻击时，没有倒置的这张卡位于前列中央的话，对手会对这张卡进行正面攻击）<br/>【自】这张卡攻击时，高潮区有「バナナフッズエンド」的话，你可以从自己的休息室选择至多2张角色卡返回手牌。这样做的话，你选择自己的1张手牌放置到休息室。",
    "all_cards": [
      {
        "id": "DC/WE08-11",
        "rarity": "R"
      }
    ],
    "trigger_soul_count": 1
  },
  "DC/WE08-12": {
    "name": "若き生徒会長 エリカ",
    "product_name": "D.C. D.C.II プラスコミュニケーション",
    "type": "角色卡",
    "level": 2,
    "power": 4500,
    "cost": 1,
    "trait": ["生徒会", "王族"],
    "color": "红色",
    "soul": 1,
    "effect": "【永】应援 你这张卡前的全部角色，战斗力+X。X是那个角色的等级×500。<br/>【自】再演 [手牌中1张角色卡放置到休息室] （这张卡从舞台放置到休息室时，你可以支付费用。支付了的话，你将这张卡横置放置到原来的位置）",
    "all_cards": [
      {
        "id": "DC/WE08-12",
        "rarity": "C"
      }
    ],
    "trigger_soul_count": 1
  },
  "DC/WE08-13": {
    "name": "“裏モード”音夢",
    "product_name": "D.C. D.C.II プラスコミュニケーション",
    "type": "角色卡",
    "level": 2,
    "power": 8500,
    "cost": 2,
    "trait": ["魔法", "風紀委員"],
    "color": "红色",
    "soul": 2,
    "effect": "【起】[你的2个角色横置] 那个回合中，这张卡的战斗力+2000。",
    "all_cards": [
      {
        "id": "DC/WE08-13",
        "rarity": "C"
      }
    ],
    "trigger_soul_count": 1
  },
  "DC/WE08-14": {
    "name": "おめかし 麻耶",
    "product_name": "D.C. D.C.II プラスコミュニケーション",
    "type": "角色卡",
    "level": 0,
    "power": 1000,
    "cost": 0,
    "trait": ["委員長", "メガネ"],
    "color": "蓝色",
    "soul": 1,
    "effect": "【永】对手的回合中，你其他全部角色，战斗力+500。<br/>【起】[手牌中1张高潮卡放置到休息室，你的2个角色横置] 你从自己的卡组找至多1张拥有『变身』能力的角色卡展示给对手后加入手牌る。卡组洗切。",
    "all_cards": [
      {
        "id": "DC/WE08-14",
        "rarity": "R"
      }
    ],
    "trigger_soul_count": 0
  },
  "DC/WE08-15": {
    "name": "恥ずかしがり屋 まゆき",
    "product_name": "D.C. D.C.II プラスコミュニケーション",
    "type": "角色卡",
    "level": 1,
    "power": 6500,
    "cost": 1,
    "trait": ["生徒会", "スポーツ"],
    "color": "蓝色",
    "soul": 1,
    "effect": "【自】这张卡攻击时，高潮区有「ロマンチックなキス」的话，你公开自己卡组顶1张卡。那张卡是《生徒会》的角色卡的话加入手牌。（否则放回原处）",
    "all_cards": [
      {
        "id": "DC/WE08-15",
        "rarity": "R"
      }
    ],
    "trigger_soul_count": 0
  },
  "DC/WE08-16": {
    "name": "水着の眞子＆萌",
    "product_name": "D.C. D.C.II プラスコミュニケーション",
    "type": "角色卡",
    "level": 0,
    "power": 3000,
    "cost": 0,
    "trait": ["音楽", "鍋"],
    "color": "蓝色",
    "soul": 1,
    "effect": "",
    "all_cards": [
      {
        "id": "DC/WE08-16",
        "rarity": "C"
      }
    ],
    "trigger_soul_count": 0
  },
  "DC/WE08-17": {
    "name": "知略と謀略 杏",
    "product_name": "D.C. D.C.II プラスコミュニケーション",
    "type": "角色卡",
    "level": 2,
    "power": 2500,
    "cost": 1,
    "trait": ["演劇", "生徒会"],
    "color": "蓝色",
    "soul": 1,
    "effect": "【起】【反击】助太刀3000 等级2 [(1) 手牌中这张卡放置到休息室] （你选择自己1个被正面攻击的角色，那个回合中，战斗力+3000）",
    "all_cards": [
      {
        "id": "DC/WE08-17",
        "rarity": "C"
      }
    ],
    "trigger_soul_count": 1
  },
  "DC/WE08-18": {
    "name": "ロマンチックなキス",
    "product_name": "D.C. D.C.II プラスコミュニケーション",
    "type": "高潮卡",
    "level": "-",
    "power": "-",
    "cost": "-",
    "trait": "-",
    "color": "蓝色",
    "soul": "-",
    "effect": "【自】这张卡从手牌放置到高潮区时，你抽1张卡，选择自己的1个角色，那个回合中，灵魂值+3。",
    "all_cards": [
      {
        "id": "DC/WE08-18",
        "rarity": "C"
      }
    ],
    "trigger_soul_count": 2
  },
  "DC/WE08-19": {
    "name": "芳乃家の居候 アイシア",
    "product_name": "D.C. D.C.II プラスコミュニケーション",
    "type": "角色卡",
    "level": 0,
    "power": 2500,
    "cost": 0,
    "trait": ["魔法", "オモチャ"],
    "color": "黄色",
    "soul": 1,
    "effect": "【起】[(2)] 你选择自己其他1个角色，那个回合中，灵魂值+1，这张卡的灵魂值+1。",
    "all_cards": [
      {
        "id": "DC/WE08-19",
        "rarity": "R"
      }
    ],
    "trigger_soul_count": 0
  },
  "DC/WE08-20": {
    "name": "たとえ好きな恋人 まひる",
    "product_name": "D.C. D.C.II プラスコミュニケーション",
    "type": "角色卡",
    "level": 2,
    "power": 8000,
    "cost": 1,
    "trait": ["たとえ話"],
    "color": "黄色",
    "soul": 1,
    "effect": "【起】[这张卡思出] 你选择自己1个《お菓子》的角色，那个回合中，战斗力+4000，灵魂值+2。",
    "all_cards": [
      {
        "id": "DC/WE08-20",
        "rarity": "C"
      }
    ],
    "trigger_soul_count": 1
  },
  "DC/WE08-21": {
    "name": "夢じゃない",
    "product_name": "D.C. D.C.II プラスコミュニケーション",
    "type": "高潮卡",
    "level": "-",
    "power": "-",
    "cost": "-",
    "trait": "-",
    "color": "绿色",
    "soul": "-",
    "effect": "【永】你的全部角色，灵魂值+2。",
    "all_cards": [
      {
        "id": "DC/WE08-21",
        "rarity": "C"
      }
    ],
    "trigger_soul_count": 2
  },
  "DC/WE08-22": {
    "name": "沢井 美秋",
    "product_name": "D.C. D.C.II プラスコミュニケーション",
    "type": "角色卡",
    "level": 1,
    "power": 5000,
    "cost": 0,
    "trait": ["メカ", "バナナ"],
    "color": "红色",
    "soul": 1,
    "effect": "【自】这张卡从手牌放置到舞台时，你选择自己1个《委員長》的角色，那个回合中，战斗力+1000。",
    "all_cards": [
      {
        "id": "DC/WE08-22",
        "rarity": "C"
      }
    ],
    "trigger_soul_count": 0
  },
  "DC/WE08-23": {
    "name": "デートを楽しむエリカ",
    "product_name": "D.C. D.C.II プラスコミュニケーション",
    "type": "角色卡",
    "level": 1,
    "power": 5500,
    "cost": 1,
    "trait": ["生徒会", "王族"],
    "color": "红色",
    "soul": 1,
    "effect": "【永】你其他《生徒会》的角色有3个以上的话，这张卡的战斗力+1000。",
    "all_cards": [
      {
        "id": "DC/WE08-23",
        "rarity": "R"
      }
    ],
    "trigger_soul_count": 1
  },
  "DC/WE08-24": {
    "name": "バナナフッズエンド",
    "product_name": "D.C. D.C.II プラスコミュニケーション",
    "type": "高潮卡",
    "level": "-",
    "power": "-",
    "cost": "-",
    "trait": "-",
    "color": "红色",
    "soul": "-",
    "effect": "【自】这张卡从手牌放置到高潮区时，你将自己卡组顶1张卡放置到库存区，自己的全部角色，那个回合中，灵魂值+1。",
    "all_cards": [
      {
        "id": "DC/WE08-24",
        "rarity": "C"
      }
    ],
    "trigger_soul_count": 2
  },
  "DC/WE08-25": {
    "name": "優等生の委員長 沢井麻耶",
    "product_name": "D.C. D.C.II プラスコミュニケーション",
    "type": "角色卡",
    "level": 0,
    "power": 3000,
    "cost": 0,
    "trait": ["委員長", "メガネ"],
    "color": "蓝色",
    "soul": 1,
    "effect": "",
    "all_cards": [
      {
        "id": "DC/WE08-25",
        "rarity": "C"
      }
    ],
    "trigger_soul_count": 0
  },
  "DC/WE08-26": {
    "name": "結婚式の歌姫",
    "product_name": "D.C. D.C.II プラスコミュニケーション",
    "type": "高潮卡",
    "level": "-",
    "power": "-",
    "cost": "-",
    "trait": "-",
    "color": "绿色",
    "soul": "-",
    "effect": "【永】你的全部角色战斗力+1000，灵魂值+1。<br/>（<img src=\"/effect-icons/treasure.webp\">：这张卡被触发时，你将这张卡返回手牌。你可以将自己卡组顶1张卡放置到库存区）",
    "all_cards": [
      {
        "id": "DC/WE08-26",
        "rarity": "C"
      }
    ],
    "trigger_soul_count": 0
  },
  "DC/WE08-27": {
    "name": "迷子の夢",
    "product_name": "D.C. D.C.II プラスコミュニケーション",
    "type": "高潮卡",
    "level": "-",
    "power": "-",
    "cost": "-",
    "trait": "-",
    "color": "红色",
    "soul": "-",
    "effect": "【自】这张卡从手牌放置到高潮区时，你抽1张卡，选择自己的1个角色，那个回合中，灵魂值+3。",
    "all_cards": [
      {
        "id": "DC/WE08-27",
        "rarity": "C"
      }
    ],
    "trigger_soul_count": 2
  },
  "DC/WE08-28": {
    "name": "水着の音姫",
    "product_name": "D.C. D.C.II プラスコミュニケーション",
    "type": "角色卡",
    "level": 0,
    "power": 2000,
    "cost": 0,
    "trait": ["生徒会", "水着"],
    "color": "黄色",
    "soul": 1,
    "effect": "【自】这张卡攻击时，你的全部角色在那个回合中，战斗力+500。",
    "all_cards": [
      {
        "id": "DC/WE08-28",
        "rarity": "R"
      }
    ],
    "trigger_soul_count": 0
  },
  "DC/WE08-29": {
    "name": "水着の音夢＆さくら",
    "product_name": "D.C. D.C.II プラスコミュニケーション",
    "type": "角色卡",
    "level": 0,
    "power": 1000,
    "cost": 0,
    "trait": ["魔法", "水着"],
    "color": "黄色",
    "soul": 1,
    "effect": "【永】应援 你这张卡前的全部角色，战斗力+500。",
    "all_cards": [
      {
        "id": "DC/WE08-29",
        "rarity": "C"
      }
    ],
    "trigger_soul_count": 0
  },
  "DC/WE08-30": {
    "name": "水着の由夢＆さくら",
    "product_name": "D.C. D.C.II プラスコミュニケーション",
    "type": "角色卡",
    "level": 1,
    "power": 5500,
    "cost": 1,
    "trait": ["魔法", "水着"],
    "color": "黄色",
    "soul": 1,
    "effect": "【自】这张卡从手牌放置到舞台时，你公开自己卡组顶1张卡。那张卡是等级1以上的卡的话，那个回合中，这张卡的灵魂值+1。（公开的卡放回原处。高潮卡视为0级）",
    "all_cards": [
      {
        "id": "DC/WE08-30",
        "rarity": "C"
      }
    ],
    "trigger_soul_count": 1
  },
  "DC/WE08-31": {
    "name": "水着の和泉子",
    "product_name": "D.C. D.C.II プラスコミュニケーション",
    "type": "角色卡",
    "level": 2,
    "power": 6500,
    "cost": 1,
    "trait": ["宇宙人", "水着"],
    "color": "黄色",
    "soul": 1,
    "effect": "【自】这张卡攻击时，你公开自己卡组顶1张卡。那张卡是高潮卡的话，你选择对手至多2个角色返回手牌。（公开的卡放回原处）",
    "all_cards": [
      {
        "id": "DC/WE08-31",
        "rarity": "C"
      }
    ],
    "trigger_soul_count": 1
  },
  "DC/WE08-32": {
    "name": "水着のななか",
    "product_name": "D.C. D.C.II プラスコミュニケーション",
    "type": "角色卡",
    "level": 1,
    "power": 7000,
    "cost": 2,
    "trait": ["音楽", "水着"],
    "color": "绿色",
    "soul": 1,
    "effect": "【自】这张卡从手牌放置到舞台时，你公开自己卡组顶1张卡。那张卡是等级1以上的卡的话放置到库存区。（否则放回原处。高潮卡视为0级）",
    "all_cards": [
      {
        "id": "DC/WE08-32",
        "rarity": "R"
      }
    ],
    "trigger_soul_count": 1
  },
  "DC/WE08-33": {
    "name": "水着のことり",
    "product_name": "D.C. D.C.II プラスコミュニケーション",
    "type": "角色卡",
    "level": 2,
    "power": 8500,
    "cost": 2,
    "trait": ["音楽", "水着"],
    "color": "绿色",
    "soul": 2,
    "effect": "【永】你有其他《先生》的角色的话，这张卡获得『【自】再演 [手牌中1张角色卡放置到休息室]』的能力。",
    "all_cards": [
      {
        "id": "DC/WE08-33",
        "rarity": "R"
      }
    ],
    "trigger_soul_count": 1
  },
  "DC/WE08-34": {
    "name": "水着の小恋",
    "product_name": "D.C. D.C.II プラスコミュニケーション",
    "type": "角色卡",
    "level": 0,
    "power": 2000,
    "cost": 0,
    "trait": ["音楽", "水着"],
    "color": "绿色",
    "soul": 1,
    "effect": "【起】[你2个《音楽》的角色横置] 你选择自己的1个角色，那个回合中，战斗力+2000。",
    "all_cards": [
      {
        "id": "DC/WE08-34",
        "rarity": "C"
      }
    ],
    "trigger_soul_count": 0
  },
  "DC/WE08-35": {
    "name": "水着のななか＆由夢",
    "product_name": "D.C. D.C.II プラスコミュニケーション",
    "type": "角色卡",
    "level": 0,
    "power": 2500,
    "cost": 0,
    "trait": ["音楽", "水着"],
    "color": "绿色",
    "soul": 1,
    "effect": "【自】这张卡从手牌放置到舞台时，你公开自己卡组顶1张卡。那张卡是等级1以上的卡的话，那个回合中，这张卡的战斗力+2000。（公开的卡放回原处。高潮卡视为0级）",
    "all_cards": [
      {
        "id": "DC/WE08-35",
        "rarity": "C"
      }
    ],
    "trigger_soul_count": 0
  },
  "DC/WE08-36": {
    "name": "水着の環",
    "product_name": "D.C. D.C.II プラスコミュニケーション",
    "type": "角色卡",
    "level": 1,
    "power": 1500,
    "cost": 0,
    "trait": ["巫女", "水着"],
    "color": "绿色",
    "soul": 1,
    "effect": "【自】这张卡从手牌放置到舞台时，你看对手卡组顶至多2张卡选择至多1张卡放置到卡组底。其余的卡按喜欢的顺序放回卡组顶。",
    "all_cards": [
      {
        "id": "DC/WE08-36",
        "rarity": "C"
      }
    ],
    "trigger_soul_count": 0
  },
  "DC/WE08-37": {
    "name": "スイカ割り",
    "product_name": "D.C. D.C.II プラスコミュニケーション",
    "type": "事件卡",
    "level": 1,
    "power": "-",
    "cost": 0,
    "trait": "-",
    "color": "绿色",
    "soul": "-",
    "effect": "你公开自己卡组顶1张卡。那张卡是高潮卡的话，你将自己卡组顶2张卡放置到库存区。（否则放回原处）",
    "all_cards": [
      {
        "id": "DC/WE08-37",
        "rarity": "C"
      }
    ],
    "trigger_soul_count": 0
  },
  "DC/WE08-38": {
    "name": "水着の音夢",
    "product_name": "D.C. D.C.II プラスコミュニケーション",
    "type": "角色卡",
    "level": 1,
    "power": 5500,
    "cost": 1,
    "trait": ["魔法", "水着"],
    "color": "红色",
    "soul": 1,
    "effect": "【自】再演 [手牌中1张角色卡放置到休息室] （这张卡从舞台放置到休息室时，你可以支付费用。支付了的话，你将这张卡横置放置到原来的位置）",
    "all_cards": [
      {
        "id": "DC/WE08-38",
        "rarity": "R"
      }
    ],
    "trigger_soul_count": 1
  },
  "DC/WE08-39": {
    "name": "水着の美春",
    "product_name": "D.C. D.C.II プラスコミュニケーション",
    "type": "角色卡",
    "level": 0,
    "power": 2000,
    "cost": 0,
    "trait": ["バナナ", "水着"],
    "color": "红色",
    "soul": 1,
    "effect": "【起】[这张卡横置] 你从自己的休息室选择1张《人形》的角色卡返回手牌。你选择自己的1张手牌放置到休息室。",
    "all_cards": [
      {
        "id": "DC/WE08-39",
        "rarity": "C"
      }
    ],
    "trigger_soul_count": 0
  },
  "DC/WE08-40": {
    "name": "水着の由夢",
    "product_name": "D.C. D.C.II プラスコミュニケーション",
    "type": "角色卡",
    "level": 3,
    "power": 9000,
    "cost": 2,
    "trait": ["魔法", "水着"],
    "color": "红色",
    "soul": 2,
    "effect": "【自】这张卡从手牌放置到舞台时，你看自己卡组顶至多4张卡，按喜欢的顺序放回卡组顶。<br/>【自】这张卡攻击时，高潮区有「ねことお風呂で」的话，你从自己的休息室选择1张角色卡返回手牌。",
    "all_cards": [
      {
        "id": "DC/WE08-40",
        "rarity": "C"
      }
    ],
    "trigger_soul_count": 1
  },
  "DC/WE08-41": {
    "name": "ねことお風呂で",
    "product_name": "D.C. D.C.II プラスコミュニケーション",
    "type": "高潮卡",
    "level": "-",
    "power": "-",
    "cost": "-",
    "trait": "-",
    "color": "红色",
    "soul": "-",
    "effect": "【永】你的全部角色战斗力+1000，灵魂值+1。",
    "all_cards": [
      {
        "id": "DC/WE08-41",
        "rarity": "C"
      }
    ],
    "trigger_soul_count": 2
  },
  "DC/WE08-42": {
    "name": "小悪魔 杏",
    "product_name": "D.C. D.C.II プラスコミュニケーション",
    "type": "角色卡",
    "level": 0,
    "power": 2500,
    "cost": 0,
    "trait": ["魔法", "水着"],
    "color": "蓝色",
    "soul": 1,
    "effect": "【自】这张卡从手牌放置到舞台时，你看自己卡组顶1张卡，放置到卡组顶或卡组底。",
    "all_cards": [
      {
        "id": "DC/WE08-42",
        "rarity": "R"
      }
    ],
    "trigger_soul_count": 0
  },
  "DC/WE08-43": {
    "name": "水着のアリス",
    "product_name": "D.C. D.C.II プラスコミュニケーション",
    "type": "角色卡",
    "level": 1,
    "power": 1000,
    "cost": 1,
    "trait": ["人形", "水着"],
    "color": "蓝色",
    "soul": 1,
    "effect": "【自】这张卡从手牌放置到舞台时，你公开自己卡组顶1张卡。那张卡是等级在自己等级以下的角色卡的话，可以放置到舞台任意位置。（否则放回原处）",
    "all_cards": [
      {
        "id": "DC/WE08-43",
        "rarity": "R"
      }
    ],
    "trigger_soul_count": 1
  },
  "DC/WE08-44": {
    "name": "水着の麻耶",
    "product_name": "D.C. D.C.II プラスコミュニケーション",
    "type": "角色卡",
    "level": 2,
    "power": 2500,
    "cost": 1,
    "trait": ["委員長", "水着"],
    "color": "蓝色",
    "soul": 1,
    "effect": "【起】【反击】助太刀3000 等级2 [(1) 手牌中这张卡放置到休息室] （你选择自己1个被正面攻击的角色，那个回合中，战斗力+3000）",
    "all_cards": [
      {
        "id": "DC/WE08-44",
        "rarity": "C"
      }
    ],
    "trigger_soul_count": 1
  },
  "DC/WE08-45": {
    "name": "小川で遊ぼう！",
    "product_name": "D.C. D.C.II プラスコミュニケーション",
    "type": "事件卡",
    "level": 1,
    "power": "-",
    "cost": 0,
    "trait": "-",
    "color": "蓝色",
    "soul": "-",
    "effect": "你抽至多2张卡，选择自己的2张手牌放置到卡组顶。",
    "all_cards": [
      {
        "id": "DC/WE08-45",
        "rarity": "C"
      }
    ],
    "trigger_soul_count": 0
  },
  "DC/WE08-46": {
    "name": "サンタのアイシア",
    "product_name": "D.C. D.C.II プラスコミュニケーション",
    "type": "角色卡",
    "level": 2,
    "power": 8500,
    "cost": 2,
    "trait": ["魔法", "オモチャ"],
    "color": "黄色",
    "soul": 2,
    "effect": "【自】[手牌中3张等级1以上的角色卡放置到休息室] 这个能力1回合至多发动1次。这张卡攻击时，高潮区有「我がままなアイシア」的话，你可以支付费用。支付了的话，你选择自己1个倒置的角色，竖置。",
    "all_cards": [
      {
        "id": "DC/WE08-46",
        "rarity": "R"
      }
    ],
    "trigger_soul_count": 1
  },
  "DC/WE08-47": {
    "name": "お雛様 音姫",
    "product_name": "D.C. D.C.II プラスコミュニケーション",
    "type": "角色卡",
    "level": 0,
    "power": 2500,
    "cost": 0,
    "trait": ["生徒会", "和服"],
    "color": "黄色",
    "soul": 1,
    "effect": "【自】这张卡攻击时，你公开自己卡组顶1张卡。那张卡是《生徒会》的角色卡的话，那个回合中，这张卡的灵魂值+1。（公开的卡放回原处）",
    "all_cards": [
      {
        "id": "DC/WE08-47",
        "rarity": "R"
      }
    ],
    "trigger_soul_count": 0
  },
  "DC/WE08-48": {
    "name": "魂を送るまひる",
    "product_name": "D.C. D.C.II プラスコミュニケーション",
    "type": "角色卡",
    "level": 1,
    "power": 5000,
    "cost": 1,
    "trait": ["たとえ話"],
    "color": "黄色",
    "soul": 1,
    "effect": "【永】这张卡不会被对手的效果选择。<br/>【自】这张卡从舞台放置到休息室时，这张卡思出。",
    "all_cards": [
      {
        "id": "DC/WE08-48",
        "rarity": "C"
      }
    ],
    "trigger_soul_count": 1
  },
  "DC/WE08-49": {
    "name": "贅沢な悩み",
    "product_name": "D.C. D.C.II プラスコミュニケーション",
    "type": "事件卡",
    "level": 1,
    "power": "-",
    "cost": 0,
    "trait": "-",
    "color": "黄色",
    "soul": "-",
    "effect": "你选择自己的1个角色，那个回合中，战斗力+1000。<br/>那个回合中，对手不能使用『【自】再演』。（规则的『【自】再演 [(3)]』也不能使用）",
    "all_cards": [
      {
        "id": "DC/WE08-49",
        "rarity": "C"
      }
    ],
    "trigger_soul_count": 0
  },
  "DC/WE08-50": {
    "name": "我がままなアイシア",
    "product_name": "D.C. D.C.II プラスコミュニケーション",
    "type": "高潮卡",
    "level": "-",
    "power": "-",
    "cost": "-",
    "trait": "-",
    "color": "黄色",
    "soul": "-",
    "effect": "【永】你的全部角色，灵魂值+2。",
    "all_cards": [
      {
        "id": "DC/WE08-50",
        "rarity": "C"
      }
    ],
    "trigger_soul_count": 2
  },
  "DC/WE08-51": {
    "name": "旅立つ茜",
    "product_name": "D.C. D.C.II プラスコミュニケーション",
    "type": "角色卡",
    "level": 2,
    "power": 8000,
    "cost": 1,
    "trait": ["特徴なし"],
    "color": "绿色",
    "soul": 1,
    "effect": "【自】这张卡攻击时，高潮区有「一緒に食べよ♪」的话，你选择自己其他1个角色，那个回合中，战斗力+3000，这张卡的战斗力+3000。",
    "all_cards": [
      {
        "id": "DC/WE08-51",
        "rarity": "R"
      }
    ],
    "trigger_soul_count": 1
  },
  "DC/WE08-52": {
    "name": "歌姫ななか",
    "product_name": "D.C. D.C.II プラスコミュニケーション",
    "type": "角色卡",
    "level": 1,
    "power": 5000,
    "cost": 0,
    "trait": ["音楽", "魔法"],
    "color": "绿色",
    "soul": 1,
    "effect": "【自】这张卡攻击时，你公开自己卡组顶1张卡。那张卡是《音楽》的角色卡的话，那个回合中，这张卡的战斗力+2000。（公开的卡放回原处）",
    "all_cards": [
      {
        "id": "DC/WE08-52",
        "rarity": "C"
      }
    ],
    "trigger_soul_count": 0
  },
  "DC/WE08-53": {
    "name": "ハロウィン小恋",
    "product_name": "D.C. D.C.II プラスコミュニケーション",
    "type": "角色卡",
    "level": 0,
    "power": 3000,
    "cost": 0,
    "trait": ["音楽", "かぼちゃ"],
    "color": "绿色",
    "soul": 1,
    "effect": "",
    "all_cards": [
      {
        "id": "DC/WE08-53",
        "rarity": "C"
      }
    ],
    "trigger_soul_count": 0
  },
  "DC/WE08-54": {
    "name": "一緒に食べよ♪",
    "product_name": "D.C. D.C.II プラスコミュニケーション",
    "type": "高潮卡",
    "level": "-",
    "power": "-",
    "cost": "-",
    "trait": "-",
    "color": "绿色",
    "soul": "-",
    "effect": "【自】这张卡从手牌放置到高潮区时，你将自己卡组顶1张卡放置到库存区，自己的全部角色，那个回合中，灵魂值+1。",
    "all_cards": [
      {
        "id": "DC/WE08-54",
        "rarity": "C"
      }
    ],
    "trigger_soul_count": 2
  },
  "DC/WE08-55": {
    "name": "水着のエリカ",
    "product_name": "D.C. D.C.II プラスコミュニケーション",
    "type": "角色卡",
    "level": 2,
    "power": 7500,
    "cost": 2,
    "trait": ["生徒会", "水着"],
    "color": "红色",
    "soul": 2,
    "effect": "【永】你每有1个其他拥有『【自】再演 [手牌中1张角色卡放置到休息室]』的角色，这张卡的战斗力+500。<br/>【自】这张卡攻击时，高潮区有「寝ぼけるエリカ」的话，你从自己的休息室选择1张角色卡返回手牌。",
    "all_cards": [
      {
        "id": "DC/WE08-55",
        "rarity": "R"
      }
    ],
    "trigger_soul_count": 1
  },
  "DC/WE08-56": {
    "name": "豆まき美夏",
    "product_name": "D.C. D.C.II プラスコミュニケーション",
    "type": "角色卡",
    "level": 1,
    "power": 4500,
    "cost": 1,
    "trait": ["メカ", "バナナ"],
    "color": "红色",
    "soul": 1,
    "effect": "【永】你有其他卡名含有「杏」的角色的话，这张卡获得以下能力。『【自】这张卡的战斗对手倒置时，你可以将那个角色放置到卡组顶。』<br/>【永】你有其他《委員長》的角色的话，这张卡的战斗力+1000。",
    "all_cards": [
      {
        "id": "DC/WE08-56",
        "rarity": "C"
      }
    ],
    "trigger_soul_count": 1
  },
  "DC/WE08-57": {
    "name": "お月見 由夢",
    "product_name": "D.C. D.C.II プラスコミュニケーション",
    "type": "角色卡",
    "level": 0,
    "power": 2500,
    "cost": 0,
    "trait": ["魔法", "だんご"],
    "color": "红色",
    "soul": 1,
    "effect": "【自】这张卡从手牌放置到舞台时，你看自己卡组顶1张卡，放置到卡组顶或休息室。",
    "all_cards": [
      {
        "id": "DC/WE08-57",
        "rarity": "C"
      }
    ],
    "trigger_soul_count": 0
  },
  "DC/WE08-58": {
    "name": "寝ぼけるエリカ",
    "product_name": "D.C. D.C.II プラスコミュニケーション",
    "type": "高潮卡",
    "level": "-",
    "power": "-",
    "cost": "-",
    "trait": "-",
    "color": "红色",
    "soul": "-",
    "effect": "【永】你的全部角色战斗力+1000，灵魂值+1。<br/>（<img src=\"/effect-icons/salvage.webp\">：这张卡被触发时，你可以从自己的休息室选择1张角色卡返回手牌）",
    "all_cards": [
      {
        "id": "DC/WE08-58",
        "rarity": "C"
      }
    ],
    "trigger_soul_count": 0
  },
  "DC/WE08-59": {
    "name": "星に願う杏",
    "product_name": "D.C. D.C.II プラスコミュニケーション",
    "type": "角色卡",
    "level": 1,
    "power": 4500,
    "cost": 0,
    "trait": ["和服", "演劇"],
    "color": "蓝色",
    "soul": 1,
    "effect": "【自】这张卡从手牌放置到舞台时，你看自己卡组顶至多2张卡，按喜欢的顺序放回卡组顶。",
    "all_cards": [
      {
        "id": "DC/WE08-59",
        "rarity": "R"
      }
    ],
    "trigger_soul_count": 0
  },
  "DC/WE08-60": {
    "name": "ボランティア巫女 麻耶",
    "product_name": "D.C. D.C.II プラスコミュニケーション",
    "type": "角色卡",
    "level": 1,
    "power": 4000,
    "cost": 0,
    "trait": ["委員長", "巫女"],
    "color": "蓝色",
    "soul": 1,
    "effect": "【自】你的「委員長の巫女姿」放置到高潮区时，你公开自己卡组顶1张卡。那张卡是《メカ》的角色卡的话放置到库存区。（否则放回原处）<br/>【起】[(1) 这张卡横置] 你公开自己卡组顶1张卡。那张卡是《メカ》的角色卡的话加入手牌。（否则放回原处）",
    "all_cards": [
      {
        "id": "DC/WE08-60",
        "rarity": "C"
      }
    ],
    "trigger_soul_count": 0
  },
  "DC/WE08-61": {
    "name": "アジサイ畑のまゆき",
    "product_name": "D.C. D.C.II プラスコミュニケーション",
    "type": "角色卡",
    "level": 0,
    "power": 1000,
    "cost": 0,
    "trait": ["生徒会", "傘"],
    "color": "蓝色",
    "soul": 1,
    "effect": "【永】你其他全部《生徒会》的角色，给予『【自】再演 [手牌中1张角色卡放置到休息室]』的能力。",
    "all_cards": [
      {
        "id": "DC/WE08-61",
        "rarity": "R"
      }
    ],
    "trigger_soul_count": 0
  },
  "DC/WE08-62": {
    "name": "ごめんね。そして、ありがとう",
    "product_name": "D.C. D.C.II プラスコミュニケーション",
    "type": "事件卡",
    "level": 2,
    "power": "-",
    "cost": 2,
    "trait": "-",
    "color": "蓝色",
    "soul": "-",
    "effect": "你没有《生徒会》的角色的话，这张卡不能从手牌中使用。<br/>你从自己的时计区选择1张卡返回手牌。这张卡思出。",
    "all_cards": [
      {
        "id": "DC/WE08-62",
        "rarity": "C"
      }
    ],
    "trigger_soul_count": 0
  },
  "DC/WE08-63": {
    "name": "委員長の巫女姿",
    "product_name": "D.C. D.C.II プラスコミュニケーション",
    "type": "高潮卡",
    "level": "-",
    "power": "-",
    "cost": "-",
    "trait": "-",
    "color": "蓝色",
    "soul": "-",
    "effect": "【自】这张卡从手牌放置到高潮区时，你抽1张卡，选择自己的1个角色，那个回合中，灵魂值+3。",
    "all_cards": [
      {
        "id": "DC/WE08-63",
        "rarity": "C"
      }
    ],
    "trigger_soul_count": 2
  },
  "DC/WE08-64": {
    "name": "芳乃 さくら",
    "product_name": "D.C. D.C.II プラスコミュニケーション",
    "type": "角色卡",
    "level": 1,
    "power": 2000,
    "cost": 1,
    "trait": ["魔法", "先生"],
    "color": "黄色",
    "soul": 1,
    "effect": "【起】【反击】助太刀2000 等级1 [(1) 手牌中这张卡放置到休息室] （你选择自己1个被正面攻击的角色，那个回合中，战斗力+2000）",
    "all_cards": [
      {
        "id": "DC/WE08-64",
        "rarity": "C"
      }
    ],
    "trigger_soul_count": 1
  },
  "DC/WE08-65": {
    "name": "決意",
    "product_name": "D.C. D.C.II プラスコミュニケーション",
    "type": "事件卡",
    "level": 1,
    "power": "-",
    "cost": 0,
    "trait": "-",
    "color": "黄色",
    "soul": "-",
    "effect": "你选择自己1个《魔法》的角色，那个回合中，战斗力+2000，灵魂值+2。回合结束时，那个角色思出。",
    "all_cards": [
      {
        "id": "DC/WE08-65",
        "rarity": "C"
      }
    ],
    "trigger_soul_count": 0
  },
  "DC/WE08-66": {
    "name": "花咲 茜",
    "product_name": "D.C. D.C.II プラスコミュニケーション",
    "type": "角色卡",
    "level": 0,
    "power": 2500,
    "cost": 0,
    "trait": ["特徴なし"],
    "color": "绿色",
    "soul": 1,
    "effect": "【起】[(1)] 那个回合中，这张卡的战斗力+2000。",
    "all_cards": [
      {
        "id": "DC/WE08-66",
        "rarity": "C"
      }
    ],
    "trigger_soul_count": 0
  },
  "DC/WE08-67": {
    "name": "ミス風見学園コンテスト",
    "product_name": "D.C. D.C.II プラスコミュニケーション",
    "type": "事件卡",
    "level": 1,
    "power": "-",
    "cost": 0,
    "trait": "-",
    "color": "绿色",
    "soul": "-",
    "effect": "你将自己卡组顶1张卡放置到库存区。你选择自己的1个角色，那个回合中，战斗力+500。",
    "all_cards": [
      {
        "id": "DC/WE08-67",
        "rarity": "C"
      }
    ],
    "trigger_soul_count": 0
  },
  "DC/WE08-68": {
    "name": "ロボ美春",
    "product_name": "D.C. D.C.II プラスコミュニケーション",
    "type": "角色卡",
    "level": 1,
    "power": 4500,
    "cost": 1,
    "trait": ["メカ", "バナナ"],
    "color": "红色",
    "soul": 1,
    "effect": "【自】这张卡的战斗对手倒置时，你可以将那个角色放置到卡组顶。<br/>【自】[(1)] 这张卡攻击时，高潮区有「美春のオルゴール」的话，你可以支付费用。支付了的话，你从自己的休息室选择1张角色卡返回手牌。",
    "all_cards": [
      {
        "id": "DC/WE08-68",
        "rarity": "C"
      }
    ],
    "trigger_soul_count": 1
  },
  "DC/WE08-69": {
    "name": "美春＆音夢",
    "product_name": "D.C. D.C.II プラスコミュニケーション",
    "type": "角色卡",
    "level": 2,
    "power": 9000,
    "cost": 2,
    "trait": ["魔法", "バナナ"],
    "color": "红色",
    "soul": 2,
    "effect": "",
    "all_cards": [
      {
        "id": "DC/WE08-69",
        "rarity": "C"
      }
    ],
    "trigger_soul_count": 1
  },
  "DC/WE08-70": {
    "name": "ホワイトクリスマス",
    "product_name": "D.C. D.C.II プラスコミュニケーション",
    "type": "事件卡",
    "level": 1,
    "power": "-",
    "cost": 2,
    "trait": "-",
    "color": "红色",
    "soul": "-",
    "effect": "你从自己的休息室选择至多2张角色卡返回手牌，选择自己的1张手牌放置到休息室。这张卡思出。",
    "all_cards": [
      {
        "id": "DC/WE08-70",
        "rarity": "C"
      }
    ],
    "trigger_soul_count": 0
  },
  "DC/WE08-71": {
    "name": "バナナパフェ",
    "product_name": "D.C. D.C.II プラスコミュニケーション",
    "type": "事件卡",
    "level": 2,
    "power": "-",
    "cost": 5,
    "trait": "-",
    "color": "红色",
    "soul": "-",
    "effect": "你从对手的休息室选择至多2张卡思出。这张卡思出。",
    "all_cards": [
      {
        "id": "DC/WE08-71",
        "rarity": "C"
      }
    ],
    "trigger_soul_count": 0
  },
  "DC/WE08-72": {
    "name": "人形劇",
    "product_name": "D.C. D.C.II プラスコミュニケーション",
    "type": "事件卡",
    "level": 2,
    "power": "-",
    "cost": 2,
    "trait": "-",
    "color": "蓝色",
    "soul": "-",
    "effect": "你抽至多2张卡。",
    "all_cards": [
      {
        "id": "DC/WE08-72",
        "rarity": "C"
      }
    ],
    "trigger_soul_count": 0
  }
}
