{
  "NA/W12-001": {
    "name": "“お姉さん”アリシア",
    "product_name": "魔法少女リリカルなのはA's",
    "type": "角色卡",
    "level": 1,
    "power": 2500,
    "cost": 1,
    "trait": ["特徴なし"],
    "color": "黄色",
    "soul": 1,
    "effect": "【永】应援 你这张卡前全部《クローン》或《動物》的角色，战斗力+X。X是那个角色的等级×500。<br/>【起】[(3) 手牌中1张高潮卡放置到休息室，这张卡思出] 你从自己的手牌中选择1张「“雷光”フェイト」，放置到这张卡原来的位置。",
    "all_cards": [
      {
        "id": "NA/W12-001",
        "rarity": "RR"
      }
    ],
    "trigger_soul_count": 1
  },
  "NA/W12-002": {
    "name": "“雷光”フェイト",
    "product_name": "魔法少女リリカルなのはA's",
    "type": "角色卡",
    "level": 3,
    "power": 9500,
    "cost": 2,
    "trait": ["魔法", "クローン"],
    "color": "黄色",
    "soul": 2,
    "effect": "【永】这张卡不会被对手的效果选择。<br/>【自】这张卡从手牌放置到舞台时，你的全部角色在那个回合中，灵魂值+1。<br/>【自】你的「理想との決別」放置到高潮区时，前列有这张卡的话，你从对手的休息室选择至多2张卡返回卡组。之后，卡组洗切，那个回合中，这张卡的战斗力+3000。",
    "all_cards": [
      {
        "id": "NA/W12-002",
        "rarity": "RR"
      },
      {
        "id": "NA/W12-002SP",
        "rarity": "SP"
      }
    ],
    "trigger_soul_count": 1
  },
  "NA/W12-003": {
    "name": "“ヴォルケンリッター”シグナム",
    "product_name": "魔法少女リリカルなのはA's",
    "type": "角色卡",
    "level": 0,
    "power": 2500,
    "cost": 0,
    "trait": ["魔法", "武器"],
    "color": "黄色",
    "soul": 1,
    "effect": "【起】[(1)] 你选择自己1个《武器》的角色，那个回合中，战斗力+1500。",
    "all_cards": [
      {
        "id": "NA/W12-003",
        "rarity": "R"
      },
      {
        "id": "NA/W12-003S",
        "rarity": "SR"
      }
    ],
    "trigger_soul_count": 0
  },
  "NA/W12-004": {
    "name": "使い魔 リニス",
    "product_name": "魔法少女リリカルなのはA's",
    "type": "角色卡",
    "level": 0,
    "power": 2500,
    "cost": 0,
    "trait": ["使い魔", "動物"],
    "color": "黄色",
    "soul": 1,
    "effect": "【自】[1张手牌放置到休息室，这张卡放置到休息室] 这张卡被正面攻击时，你可以支付费用。支付了的话，你从自己的手牌中选择1张「戯れるフェイト＆アルフ」，作为防御角色放置到这张卡的位置。",
    "all_cards": [
      {
        "id": "NA/W12-004",
        "rarity": "R"
      }
    ],
    "trigger_soul_count": 0
  },
  "NA/W12-005": {
    "name": "“強敵”シグナム",
    "product_name": "魔法少女リリカルなのはA's",
    "type": "角色卡",
    "level": 1,
    "power": 5000,
    "cost": 0,
    "trait": ["魔法", "武器"],
    "color": "黄色",
    "soul": 1,
    "effect": "【自】[你卡组顶1张卡放置到时计区] 这张卡从手牌放置到舞台时，你可以支付费用。支付了的话，那个回合中，这张卡的战斗力+3500。",
    "all_cards": [
      {
        "id": "NA/W12-005",
        "rarity": "R"
      }
    ],
    "trigger_soul_count": 0
  },
  "NA/W12-006": {
    "name": "武人 シグナム",
    "product_name": "魔法少女リリカルなのはA's",
    "type": "角色卡",
    "level": 2,
    "power": 8000,
    "cost": 1,
    "trait": ["魔法", "武器"],
    "color": "黄色",
    "soul": 1,
    "effect": "【自】这张卡攻击时，高潮区有「シュツルムファルケン」的话，那个回合中，这张卡的战斗力+3000，对手不能使用『【自】再演』。（规则的『【自】再演 [(3)]』也不能使用）",
    "all_cards": [
      {
        "id": "NA/W12-006",
        "rarity": "R"
      },
      {
        "id": "NA/W12-006SP",
        "rarity": "SP"
      }
    ],
    "trigger_soul_count": 1
  },
  "NA/W12-007": {
    "name": "フェイト with バルディッシュ・アサルト",
    "product_name": "魔法少女リリカルなのはA's",
    "type": "角色卡",
    "level": 2,
    "power": 7500,
    "cost": 1,
    "trait": ["魔法", "クローン"],
    "color": "黄色",
    "soul": 1,
    "effect": "【自】[你卡组顶1张卡放置到时计区] 这张卡从手牌放置到舞台时，你可以支付费用。支付了的话，那个回合中，这张卡的战斗力+4500。<br/>【自】这张卡攻击时，高潮区有「雷光一閃」的话，你可以选择对手的1个角色，使其返回手牌。",
    "all_cards": [
      {
        "id": "NA/W12-007",
        "rarity": "R"
      }
    ],
    "trigger_soul_count": 1
  },
  "NA/W12-008": {
    "name": "剣の騎士 シグナム",
    "product_name": "魔法少女リリカルなのはA's",
    "type": "角色卡",
    "level": 0,
    "power": 500,
    "cost": 0,
    "trait": ["魔法", "武器"],
    "color": "黄色",
    "soul": 1,
    "effect": "【永】应援 你这张卡前的全部角色，战斗力+500。<br/>【起】[这张卡横置] 你选择自己1个卡名含有「八神」的角色，那个回合中，战斗力+500。",
    "all_cards": [
      {
        "id": "NA/W12-008",
        "rarity": "U"
      }
    ],
    "trigger_soul_count": 0
  },
  "NA/W12-009": {
    "name": "中学三年生のフェイト",
    "product_name": "魔法少女リリカルなのはA's",
    "type": "角色卡",
    "level": 0,
    "power": 1000,
    "cost": 0,
    "trait": ["魔法", "クローン"],
    "color": "黄色",
    "soul": 1,
    "effect": "【自】绊／「祝福するなのは」 [你卡组顶1张卡放置到时计区] （这张卡被使用放置到舞台时，你可以支付费用。支付了的话，你从自己的休息室选择1张「祝福するなのは」返回手牌）",
    "all_cards": [
      {
        "id": "NA/W12-009",
        "rarity": "U"
      }
    ],
    "trigger_soul_count": 0
  },
  "NA/W12-010": {
    "name": "“友達”フェイト",
    "product_name": "魔法少女リリカルなのはA's",
    "type": "角色卡",
    "level": 1,
    "power": 500,
    "cost": 0,
    "trait": ["魔法", "クローン"],
    "color": "黄色",
    "soul": 1,
    "effect": "【自】你使用这张卡的『助太刀』时，你有其他卡名含有「なのは」的角色的话，你将全部玩家将卡组顶3张卡放置到休息室。<br/>【起】【反击】助太刀1500 等级1 [手牌中这张卡放置到休息室] （你选择自己1个被正面攻击的角色，那个回合中，战斗力+1500）",
    "all_cards": [
      {
        "id": "NA/W12-010",
        "rarity": "U"
      }
    ],
    "trigger_soul_count": 0
  },
  "NA/W12-011": {
    "name": "ソニックフォーム フェイト",
    "product_name": "魔法少女リリカルなのはA's",
    "type": "角色卡",
    "level": 2,
    "power": 10000,
    "cost": 2,
    "trait": ["魔法", "クローン"],
    "color": "黄色",
    "soul": 2,
    "effect": "【永】这张卡正面的角色灵魂值+1。",
    "all_cards": [
      {
        "id": "NA/W12-011",
        "rarity": "U"
      }
    ],
    "trigger_soul_count": 1
  },
  "NA/W12-012": {
    "name": "“突貫”アルフ",
    "product_name": "魔法少女リリカルなのはA's",
    "type": "角色卡",
    "level": 2,
    "power": 7000,
    "cost": 2,
    "trait": ["使い魔", "動物"],
    "color": "黄色",
    "soul": 2,
    "effect": "【永】记忆 你的思出区有3张以上的话，这张卡的战斗力+1000，灵魂值+1。<br/>【自】再演 [手牌中1张角色卡放置到休息室] （这张卡从舞台放置到休息室时，你可以支付费用。支付了的话，你将这张卡横置放置到原来的位置）",
    "all_cards": [
      {
        "id": "NA/W12-012",
        "rarity": "U"
      }
    ],
    "trigger_soul_count": 1
  },
  "NA/W12-013": {
    "name": "“フェイト・T”リーゼロッテ",
    "product_name": "魔法少女リリカルなのはA's",
    "type": "角色卡",
    "level": 0,
    "power": 1500,
    "cost": 0,
    "trait": ["双子", "使い魔"],
    "color": "黄色",
    "soul": 1,
    "effect": "【自】[(1) 这张卡思出] 战斗中这张卡倒置时，你可以支付费用。支付了的话，你从对手的休息室选择1张卡返回卡组。卡组洗切。",
    "all_cards": [
      {
        "id": "NA/W12-013",
        "rarity": "C"
      }
    ],
    "trigger_soul_count": 0
  },
  "NA/W12-014": {
    "name": "超アバウト アルフ",
    "product_name": "魔法少女リリカルなのはA's",
    "type": "角色卡",
    "level": 0,
    "power": 2500,
    "cost": 0,
    "trait": ["使い魔", "動物"],
    "color": "黄色",
    "soul": 1,
    "effect": "【永】对手每有1个竖置的角色，这张卡的战斗力+500。",
    "all_cards": [
      {
        "id": "NA/W12-014",
        "rarity": "C"
      }
    ],
    "trigger_soul_count": 0
  },
  "NA/W12-015": {
    "name": "戸惑うフェイト",
    "product_name": "魔法少女リリカルなのはA's",
    "type": "角色卡",
    "level": 0,
    "power": 3000,
    "cost": 0,
    "trait": ["魔法", "クローン"],
    "color": "黄色",
    "soul": 1,
    "effect": "",
    "all_cards": [
      {
        "id": "NA/W12-015",
        "rarity": "C"
      }
    ],
    "trigger_soul_count": 0
  },
  "NA/W12-016": {
    "name": "フェイトVSシグナム",
    "product_name": "魔法少女リリカルなのはA's",
    "type": "角色卡",
    "level": 1,
    "power": 4000,
    "cost": 0,
    "trait": ["魔法", "武器"],
    "color": "黄色",
    "soul": 1,
    "effect": "【自】变身 [(3) 1张手牌放置到休息室，这张卡思出] 你的高潮阶段开始时，你可以支付费用。支付了的话，你从自己的休息室选择1张「ソニックフォーム フェイト」或「“八神家”シグナム」，放置到这张卡原来的位置。",
    "all_cards": [
      {
        "id": "NA/W12-016",
        "rarity": "C"
      }
    ],
    "trigger_soul_count": 0
  },
  "NA/W12-017": {
    "name": "戯れるフェイト＆アルフ",
    "product_name": "魔法少女リリカルなのはA's",
    "type": "角色卡",
    "level": 1,
    "power": 7000,
    "cost": 1,
    "trait": ["クローン", "使い魔"],
    "color": "黄色",
    "soul": 1,
    "effect": "",
    "all_cards": [
      {
        "id": "NA/W12-017",
        "rarity": "C"
      }
    ],
    "trigger_soul_count": 0
  },
  "NA/W12-018": {
    "name": "優しい母親 プレシア",
    "product_name": "魔法少女リリカルなのはA's",
    "type": "角色卡",
    "level": 1,
    "power": 2000,
    "cost": 1,
    "trait": ["魔法"],
    "color": "黄色",
    "soul": 1,
    "effect": "【永】你其他全部卡名含有「フェイト」的角色，给予以下能力。『【永】这张卡不会被对手的效果选择。』<br/>【永】你的回合中，你其他全部角色，战斗力+1000。",
    "all_cards": [
      {
        "id": "NA/W12-018",
        "rarity": "C"
      }
    ],
    "trigger_soul_count": 1
  },
  "NA/W12-019": {
    "name": "“八神家”シグナム",
    "product_name": "魔法少女リリカルなのはA's",
    "type": "角色卡",
    "level": 2,
    "power": 9000,
    "cost": 2,
    "trait": ["魔法", "武器"],
    "color": "黄色",
    "soul": 2,
    "effect": "",
    "all_cards": [
      {
        "id": "NA/W12-019",
        "rarity": "C"
      }
    ],
    "trigger_soul_count": 1
  },
  "NA/W12-020": {
    "name": "CVK792導入",
    "product_name": "魔法少女リリカルなのはA's",
    "type": "事件卡",
    "level": 1,
    "power": "-",
    "cost": 1,
    "trait": "-",
    "color": "黄色",
    "soul": "-",
    "effect": "【反击】你选择自己1个卡名含有「なのは」的角色，那个回合中，战斗力+1500。<br/>你选择自己1个卡名含有「フェイト」的角色，那个回合中，战斗力+1500。",
    "all_cards": [
      {
        "id": "NA/W12-020",
        "rarity": "U"
      }
    ],
    "trigger_soul_count": 0
  },
  "NA/W12-021": {
    "name": "主への想い",
    "product_name": "魔法少女リリカルなのはA's",
    "type": "事件卡",
    "level": 1,
    "power": "-",
    "cost": 3,
    "trait": "-",
    "color": "黄色",
    "soul": "-",
    "effect": "这张卡思出。<br/>记忆 思出区有这张卡的话，你全部的「“強敵”シグナム」和「“八神家”シグナム」，战斗力+1000。",
    "all_cards": [
      {
        "id": "NA/W12-021",
        "rarity": "U"
      }
    ],
    "trigger_soul_count": 0
  },
  "NA/W12-022": {
    "name": "怒涛の質問攻め",
    "product_name": "魔法少女リリカルなのはA's",
    "type": "事件卡",
    "level": 2,
    "power": "-",
    "cost": 0,
    "trait": "-",
    "color": "黄色",
    "soul": "-",
    "effect": "你从自己的卡组找至多1张《クローン》的角色卡展示给对手后加入手牌。卡组洗切。",
    "all_cards": [
      {
        "id": "NA/W12-022",
        "rarity": "C"
      }
    ],
    "trigger_soul_count": 0
  },
  "NA/W12-023": {
    "name": "雷光一閃",
    "product_name": "魔法少女リリカルなのはA's",
    "type": "高潮卡",
    "level": "-",
    "power": "-",
    "cost": "-",
    "trait": "-",
    "color": "黄色",
    "soul": "-",
    "effect": "【永】你的全部角色战斗力+1000，灵魂值+1。<br/>（<img src=\"/effect-icons/shot.webp\">：这个回合中，触发这张卡的角色下次造成的伤害被取消时，给对手造成1点伤害）",
    "all_cards": [
      {
        "id": "NA/W12-023",
        "rarity": "CR"
      },
      {
        "id": "NA/W12-023S",
        "rarity": "SR"
      }
    ],
    "trigger_soul_count": 1
  },
  "NA/W12-024": {
    "name": "理想との決別",
    "product_name": "魔法少女リリカルなのはA's",
    "type": "高潮卡",
    "level": "-",
    "power": "-",
    "cost": "-",
    "trait": "-",
    "color": "黄色",
    "soul": "-",
    "effect": "【自】这张卡从手牌放置到高潮区时，你抽1张卡，选择自己的1个角色，那个回合中，战斗力+2000，灵魂值+1。",
    "all_cards": [
      {
        "id": "NA/W12-024",
        "rarity": "CC"
      }
    ],
    "trigger_soul_count": 2
  },
  "NA/W12-025": {
    "name": "シュツルムファルケン",
    "product_name": "魔法少女リリカルなのはA's",
    "type": "高潮卡",
    "level": "-",
    "power": "-",
    "cost": "-",
    "trait": "-",
    "color": "黄色",
    "soul": "-",
    "effect": "【永】你的全部角色战斗力+1000，灵魂值+1。<br/>（<img src=\"/effect-icons/bounce.webp\">：这张卡被触发时，你可以选择对手的1个角色，使其返回手牌）",
    "all_cards": [
      {
        "id": "NA/W12-025",
        "rarity": "CC"
      }
    ],
    "trigger_soul_count": 1
  },
  "NA/W12-026": {
    "name": "アースラのNo.3 エイミィ",
    "product_name": "魔法少女リリカルなのはA's",
    "type": "角色卡",
    "level": 1,
    "power": 3500,
    "cost": 0,
    "trait": ["特徴なし"],
    "color": "绿色",
    "soul": 1,
    "effect": "【永】记忆 你的思出区有2张以上的话，你其他全部角色，战斗力+500。<br/>【自】[手牌中1张「アルカンシェル」放置到休息室] 你其他角色的等级3以上的战斗对手倒置时，你可以支付费用。支付了的话，你将那个角色放置到时计区。",
    "all_cards": [
      {
        "id": "NA/W12-026",
        "rarity": "RR"
      }
    ],
    "trigger_soul_count": 0
  },
  "NA/W12-027": {
    "name": "名コンビ クロノ＆エイミィ",
    "product_name": "魔法少女リリカルなのはA's",
    "type": "角色卡",
    "level": 2,
    "power": 8000,
    "cost": 2,
    "trait": ["魔法", "武器"],
    "color": "绿色",
    "soul": 2,
    "effect": "【永】记忆 你的思出区有3张以上的话，这张卡的战斗力+2000。",
    "all_cards": [
      {
        "id": "NA/W12-027",
        "rarity": "RR"
      }
    ],
    "trigger_soul_count": 1
  },
  "NA/W12-028": {
    "name": "はやて＆すずか",
    "product_name": "魔法少女リリカルなのはA's",
    "type": "角色卡",
    "level": 0,
    "power": 500,
    "cost": 0,
    "trait": ["本", "動物"],
    "color": "绿色",
    "soul": 1,
    "effect": "【自】[(2) 这张卡思出] 战斗中这张卡倒置时，你可以支付费用。支付了的话，你从自己的卡组找至多1张《本》的角色卡展示给对手后加入手牌。卡组洗切。",
    "all_cards": [
      {
        "id": "NA/W12-028",
        "rarity": "R"
      }
    ],
    "trigger_soul_count": 0
  },
  "NA/W12-029": {
    "name": "アリサ＆ちびアルフ",
    "product_name": "魔法少女リリカルなのはA's",
    "type": "角色卡",
    "level": 1,
    "power": 5000,
    "cost": 0,
    "trait": ["動物", "使い魔"],
    "color": "绿色",
    "soul": 1,
    "effect": "【起】[(2)] 那个回合中，这张卡的战斗力+5000。",
    "all_cards": [
      {
        "id": "NA/W12-029",
        "rarity": "R"
      },
      {
        "id": "NA/W12-029S",
        "rarity": "SR"
      }
    ],
    "trigger_soul_count": 0
  },
  "NA/W12-030": {
    "name": "“友達”すずか",
    "product_name": "魔法少女リリカルなのはA's",
    "type": "角色卡",
    "level": 1,
    "power": 3000,
    "cost": 0,
    "trait": ["動物"],
    "color": "绿色",
    "soul": 1,
    "effect": "【永】你其他全部的「“友達”アリサ」，战斗力+1000。<br/>【自】绊／「“友達”アリサ」 [(1)] （这张卡被使用放置到舞台时，你可以支付费用。支付了的话，你从自己的休息室选择1张「“友達”アリサ」返回手牌）",
    "all_cards": [
      {
        "id": "NA/W12-030",
        "rarity": "R"
      },
      {
        "id": "NA/W12-030SP",
        "rarity": "SP"
      }
    ],
    "trigger_soul_count": 0
  },
  "NA/W12-031": {
    "name": "執務官 クロノ",
    "product_name": "魔法少女リリカルなのはA's",
    "type": "角色卡",
    "level": 1,
    "power": 6500,
    "cost": 1,
    "trait": ["魔法", "武器"],
    "color": "绿色",
    "soul": 1,
    "effect": "【自】再演 [你卡组顶1张卡放置到时计区] （这张卡从舞台放置到休息室时，你可以支付费用。支付了的话，你将这张卡横置放置到原来的位置）",
    "all_cards": [
      {
        "id": "NA/W12-031",
        "rarity": "R"
      },
      {
        "id": "NA/W12-031SP",
        "rarity": "SP"
      }
    ],
    "trigger_soul_count": 0
  },
  "NA/W12-032": {
    "name": "“友達”アリサ",
    "product_name": "魔法少女リリカルなのはA's",
    "type": "角色卡",
    "level": 2,
    "power": 8500,
    "cost": 2,
    "trait": ["動物"],
    "color": "绿色",
    "soul": 2,
    "effect": "【起】[你1个《動物》的角色横置] 那个回合中，这张卡的战斗力+1000。",
    "all_cards": [
      {
        "id": "NA/W12-032",
        "rarity": "R"
      }
    ],
    "trigger_soul_count": 1
  },
  "NA/W12-033": {
    "name": "初めての学校 フェイト",
    "product_name": "魔法少女リリカルなのはA's",
    "type": "角色卡",
    "level": 0,
    "power": 2000,
    "cost": 0,
    "trait": ["魔法", "クローン"],
    "color": "绿色",
    "soul": 1,
    "effect": "【永】你其他《動物》的角色有2个以上的话，这张卡的等级+1，战斗力+1500。",
    "all_cards": [
      {
        "id": "NA/W12-033",
        "rarity": "U"
      }
    ],
    "trigger_soul_count": 0
  },
  "NA/W12-034": {
    "name": "仕切り屋 アリサ",
    "product_name": "魔法少女リリカルなのはA's",
    "type": "角色卡",
    "level": 0,
    "power": 2000,
    "cost": 0,
    "trait": ["動物"],
    "color": "绿色",
    "soul": 1,
    "effect": "【永】你每有1个其他的《動物》的角色，这张卡的战斗力+500。",
    "all_cards": [
      {
        "id": "NA/W12-034",
        "rarity": "U"
      }
    ],
    "trigger_soul_count": 0
  },
  "NA/W12-035": {
    "name": "マリエル・アテンザ",
    "product_name": "魔法少女リリカルなのはA's",
    "type": "角色卡",
    "level": 1,
    "power": 1500,
    "cost": 1,
    "trait": ["メガネ"],
    "color": "绿色",
    "soul": 1,
    "effect": "【自】你使用这张卡的『助太刀』时，你选择自己1个卡名含有「なのは」或「フェイト」的角色，那个回合中，战斗力+1000。<br/>【起】【反击】助太刀1500 等级1 [(1) 手牌中这张卡放置到休息室] （你选择自己1个被正面攻击的角色，那个回合中，战斗力+1500）",
    "all_cards": [
      {
        "id": "NA/W12-035",
        "rarity": "U"
      }
    ],
    "trigger_soul_count": 1
  },
  "NA/W12-036": {
    "name": "仲良し四人組",
    "product_name": "魔法少女リリカルなのはA's",
    "type": "角色卡",
    "level": 2,
    "power": 4000,
    "cost": 1,
    "trait": ["魔法", "動物"],
    "color": "绿色",
    "soul": 1,
    "effect": "【永】应援 你这张卡前的全部角色，战斗力+1000。<br/>【自】你的「早く良くなってね▽」放置到高潮区时，你可以将自己卡组顶1张卡放置到库存区。",
    "all_cards": [
      {
        "id": "NA/W12-036",
        "rarity": "U"
      }
    ],
    "trigger_soul_count": 1
  },
  "NA/W12-037": {
    "name": "未来を変える力 クロノ",
    "product_name": "魔法少女リリカルなのはA's",
    "type": "角色卡",
    "level": 3,
    "power": 10000,
    "cost": 2,
    "trait": ["魔法", "武器"],
    "color": "绿色",
    "soul": 2,
    "effect": "【自】这张卡从手牌放置到舞台时，你选择对手的1个角色，那个回合中，战斗力-2000。<br/>【自】这张卡攻击时，高潮区有「エターナルコフィン」的话，你将对手的全部费用放置到休息室，对手从自己的卡组顶将相同张数的卡放置到库存区。",
    "all_cards": [
      {
        "id": "NA/W12-037",
        "rarity": "U"
      }
    ],
    "trigger_soul_count": 1
  },
  "NA/W12-038": {
    "name": "エイミィ・リミエッタ",
    "product_name": "魔法少女リリカルなのはA's",
    "type": "角色卡",
    "level": 0,
    "power": 500,
    "cost": 0,
    "trait": ["特徴なし"],
    "color": "绿色",
    "soul": 1,
    "effect": "【永】应援 你这张卡前的全部角色，战斗力+500。<br/>【自】[(2)] 这张卡从手牌放置到舞台时，你可以支付费用。支付了的话，你从自己的卡组找至多1张「未来を変える力 クロノ」展示给对手后加入手牌。卡组洗切。",
    "all_cards": [
      {
        "id": "NA/W12-038",
        "rarity": "C"
      }
    ],
    "trigger_soul_count": 0
  },
  "NA/W12-039": {
    "name": "中学三年生のアリサ＆すずか",
    "product_name": "魔法少女リリカルなのはA's",
    "type": "角色卡",
    "level": 0,
    "power": 2500,
    "cost": 0,
    "trait": ["動物"],
    "color": "绿色",
    "soul": 1,
    "effect": "【自】这张卡从手牌放置到舞台时，那个回合中，这张卡的战斗力+X。X是你《動物》的角色的数量×500。",
    "all_cards": [
      {
        "id": "NA/W12-039",
        "rarity": "C"
      }
    ],
    "trigger_soul_count": 0
  },
  "NA/W12-040": {
    "name": "“お兄ちゃん”クロノ",
    "product_name": "魔法少女リリカルなのはA's",
    "type": "角色卡",
    "level": 0,
    "power": 2500,
    "cost": 0,
    "trait": ["魔法", "武器"],
    "color": "绿色",
    "soul": 1,
    "effect": "【自】战斗中这张卡倒置时，你公开自己卡组顶1张卡。那张卡是《武器》的角色卡的话，你可以将这张卡思出。（公开的卡放回原处）",
    "all_cards": [
      {
        "id": "NA/W12-040",
        "rarity": "C"
      }
    ],
    "trigger_soul_count": 0
  },
  "NA/W12-041": {
    "name": "優しい母親 リンディ",
    "product_name": "魔法少女リリカルなのはA's",
    "type": "角色卡",
    "level": 0,
    "power": 3000,
    "cost": 0,
    "trait": ["魔法", "お弁当"],
    "color": "绿色",
    "soul": 1,
    "effect": "",
    "all_cards": [
      {
        "id": "NA/W12-041",
        "rarity": "C"
      }
    ],
    "trigger_soul_count": 0
  },
  "NA/W12-042": {
    "name": "アリサ＆すずか",
    "product_name": "魔法少女リリカルなのはA's",
    "type": "角色卡",
    "level": 1,
    "power": 4500,
    "cost": 0,
    "trait": ["動物"],
    "color": "绿色",
    "soul": 1,
    "effect": "【自】变身 [(2) 1张手牌放置到休息室，这张卡思出] 你的高潮阶段开始时，你可以支付费用。支付了的话，你从自己的休息室选择1张「仲良し四人組」，放置到这张卡原来的位置。",
    "all_cards": [
      {
        "id": "NA/W12-042",
        "rarity": "C"
      }
    ],
    "trigger_soul_count": 0
  },
  "NA/W12-043": {
    "name": "無類の甘党 リンディ",
    "product_name": "魔法少女リリカルなのはA's",
    "type": "角色卡",
    "level": 2,
    "power": 6000,
    "cost": 1,
    "trait": ["魔法", "お茶"],
    "color": "绿色",
    "soul": 1,
    "effect": "【自】警铃 这张卡在时计区最上面，你《魔法》或《お茶》的角色有4个以上的话，你的高潮阶段开始时，你可以将自己卡组顶1张卡放置到库存区。",
    "all_cards": [
      {
        "id": "NA/W12-043",
        "rarity": "C"
      }
    ],
    "trigger_soul_count": 1
  },
  "NA/W12-044": {
    "name": "読書好き すずか",
    "product_name": "魔法少女リリカルなのはA's",
    "type": "角色卡",
    "level": 2,
    "power": 8500,
    "cost": 1,
    "trait": ["動物", "本"],
    "color": "绿色",
    "soul": 1,
    "effect": "",
    "all_cards": [
      {
        "id": "NA/W12-044",
        "rarity": "C"
      }
    ],
    "trigger_soul_count": 1
  },
  "NA/W12-045": {
    "name": "お宅訪問",
    "product_name": "魔法少女リリカルなのはA's",
    "type": "事件卡",
    "level": 1,
    "power": "-",
    "cost": 0,
    "trait": "-",
    "color": "绿色",
    "soul": "-",
    "effect": "你从自己的时计区选择1张《動物》的角色卡返回手牌。这张卡放置到时计区。",
    "all_cards": [
      {
        "id": "NA/W12-045",
        "rarity": "U"
      }
    ],
    "trigger_soul_count": 0
  },
  "NA/W12-046": {
    "name": "遠い日の思い出",
    "product_name": "魔法少女リリカルなのはA's",
    "type": "事件卡",
    "level": 1,
    "power": "-",
    "cost": 1,
    "trait": "-",
    "color": "绿色",
    "soul": "-",
    "effect": "你选择对手的1个角色，那个回合中，战斗力-2000。这张卡思出。",
    "all_cards": [
      {
        "id": "NA/W12-046",
        "rarity": "U"
      }
    ],
    "trigger_soul_count": 0
  },
  "NA/W12-047": {
    "name": "育んだ友情",
    "product_name": "魔法少女リリカルなのはA's",
    "type": "事件卡",
    "level": 2,
    "power": "-",
    "cost": 2,
    "trait": "-",
    "color": "绿色",
    "soul": "-",
    "effect": "【反击】你选择自己至多2个角色，那个回合中，战斗力+2000。这张卡思出。",
    "all_cards": [
      {
        "id": "NA/W12-047",
        "rarity": "C"
      }
    ],
    "trigger_soul_count": 0
  },
  "NA/W12-048": {
    "name": "アルカンシェル",
    "product_name": "魔法少女リリカルなのはA's",
    "type": "高潮卡",
    "level": "-",
    "power": "-",
    "cost": "-",
    "trait": "-",
    "color": "绿色",
    "soul": "-",
    "effect": "【永】你的全部角色战斗力+1000，灵魂值+1。<br/>（<img src=\"/effect-icons/stock.webp\">：这张卡被触发时，你可以将自己卡组顶1张卡放置到库存区）",
    "all_cards": [
      {
        "id": "NA/W12-048",
        "rarity": "CR"
      },
      {
        "id": "NA/W12-048S",
        "rarity": "SR"
      }
    ],
    "trigger_soul_count": 0
  },
  "NA/W12-049": {
    "name": "エターナルコフィン",
    "product_name": "魔法少女リリカルなのはA's",
    "type": "高潮卡",
    "level": "-",
    "power": "-",
    "cost": "-",
    "trait": "-",
    "color": "绿色",
    "soul": "-",
    "effect": "【自】这张卡从手牌放置到高潮区时，你抽1张卡，选择自己的1个角色，那个回合中，战斗力+2000，灵魂值+1。",
    "all_cards": [
      {
        "id": "NA/W12-049",
        "rarity": "CC"
      }
    ],
    "trigger_soul_count": 2
  },
  "NA/W12-050": {
    "name": "早く良くなってね♡",
    "product_name": "魔法少女リリカルなのはA's",
    "type": "高潮卡",
    "level": "-",
    "power": "-",
    "cost": "-",
    "trait": "-",
    "color": "绿色",
    "soul": "-",
    "effect": "【永】你的全部角色战斗力+1000，灵魂值+1。<br/>（<img src=\"/effect-icons/treasure.webp\">：这张卡被触发时，你将这张卡返回手牌。你可以将自己卡组顶1张卡放置到库存区）",
    "all_cards": [
      {
        "id": "NA/W12-050",
        "rarity": "CC"
      }
    ],
    "trigger_soul_count": 0
  },
  "NA/W12-051": {
    "name": "紅の鉄騎 ヴィータ",
    "product_name": "魔法少女リリカルなのはA's",
    "type": "角色卡",
    "level": 1,
    "power": 4500,
    "cost": 0,
    "trait": ["魔法", "人形"],
    "color": "红色",
    "soul": 1,
    "effect": "【自】这张卡攻击时，高潮区有「轟天爆砕」的话，那个回合中，这张卡获得以下能力。『【自】这张卡倒置时，这张卡的战斗对手的等级在这张卡的等级以下的话，你可以将那个角色倒置。』<br/>【自】[(1)] 这张卡正面攻击时，你可以支付费用。支付了的话，你选择对手的1个角色，那个回合中，等级-1。",
    "all_cards": [
      {
        "id": "NA/W12-051",
        "rarity": "RR"
      },
      {
        "id": "NA/W12-051SP",
        "rarity": "SP"
      }
    ],
    "trigger_soul_count": 0
  },
  "NA/W12-052": {
    "name": "“揺るぎ無い意志”なのは",
    "product_name": "魔法少女リリカルなのはA's",
    "type": "角色卡",
    "level": 3,
    "power": 10000,
    "cost": 2,
    "trait": ["魔法", "武器"],
    "color": "红色",
    "soul": 2,
    "effect": "【自】这张卡从手牌或通过『变身』放置到舞台时，你可以将自己时计区顶1张卡放置到休息室。<br/>【自】[(6)] 这张卡攻击时，你可以支付费用。支付了的话，给对手造成5点伤害。（发生伤害取消）",
    "all_cards": [
      {
        "id": "NA/W12-052",
        "rarity": "RR"
      },
      {
        "id": "NA/W12-052S",
        "rarity": "SR"
      }
    ],
    "trigger_soul_count": 1
  },
  "NA/W12-053": {
    "name": "中学三年生のなのは",
    "product_name": "魔法少女リリカルなのはA's",
    "type": "角色卡",
    "level": 0,
    "power": 500,
    "cost": 0,
    "trait": ["魔法", "武器"],
    "color": "红色",
    "soul": 1,
    "effect": "【自】这张卡攻击时，你全部的卡名含有「フェイト」的角色，那个回合中，战斗力+500。<br/>【自】绊／「“雷光”フェイト」 [(1)] （这张卡被使用放置到舞台时，你可以支付费用。支付了的话，你从自己的休息室选择1张「“雷光”フェイト」返回手牌）",
    "all_cards": [
      {
        "id": "NA/W12-053",
        "rarity": "R"
      }
    ],
    "trigger_soul_count": 0
  },
  "NA/W12-054": {
    "name": "“再会”なのは＆フェイト",
    "product_name": "魔法少女リリカルなのはA's",
    "type": "角色卡",
    "level": 0,
    "power": 2000,
    "cost": 0,
    "trait": ["魔法", "クローン"],
    "color": "红色",
    "soul": 1,
    "effect": "【永】这张卡的下方有指示物的话，这张卡的战斗力+2000。<br/>【起】[这张卡横置] 这张卡的下方没有指示物的话，你将自己卡组顶1张卡放置到这张卡的下方作为指示物。",
    "all_cards": [
      {
        "id": "NA/W12-054",
        "rarity": "R"
      }
    ],
    "trigger_soul_count": 0
  },
  "NA/W12-055": {
    "name": "傷ついたなのは",
    "product_name": "魔法少女リリカルなのはA's",
    "type": "角色卡",
    "level": 1,
    "power": 5500,
    "cost": 1,
    "trait": ["魔法", "武器"],
    "color": "红色",
    "soul": 1,
    "effect": "【自】[(2) 手牌中1张「I can be shot」放置到休息室] 这张卡攻击时，你可以支付费用。支付了的话，给对手造成2点伤害。（发生伤害取消）",
    "all_cards": [
      {
        "id": "NA/W12-055",
        "rarity": "R"
      }
    ],
    "trigger_soul_count": 1
  },
  "NA/W12-056": {
    "name": "闇の書の騎士 ヴィータ",
    "product_name": "魔法少女リリカルなのはA's",
    "type": "角色卡",
    "level": 2,
    "power": 7000,
    "cost": 1,
    "trait": ["魔法", "人形"],
    "color": "红色",
    "soul": 1,
    "effect": "【自】[你卡组顶1张卡放置到时计区] 这张卡从手牌放置到舞台时，你可以支付费用。支付了的话，那个回合中，这张卡的战斗力+4500。<br/>【自】再演 [手牌中1张角色卡放置到休息室] （这张卡从舞台放置到休息室时，你可以支付费用。支付了的话，你将这张卡横置放置到原来的位置）",
    "all_cards": [
      {
        "id": "NA/W12-056",
        "rarity": "R"
      }
    ],
    "trigger_soul_count": 1
  },
  "NA/W12-057": {
    "name": "なのは with レイジングハート・エクセリオン",
    "product_name": "魔法少女リリカルなのはA's",
    "type": "角色卡",
    "level": 2,
    "power": 7500,
    "cost": 2,
    "trait": ["魔法", "武器"],
    "color": "红色",
    "soul": 2,
    "effect": "【自】[你卡组顶1张卡放置到时计区] 这张卡从手牌放置到舞台时，你可以支付费用。支付了的话，那个回合中，这张卡的战斗力+4500。<br/>【自】变身 [(1) 1张手牌放置到休息室，这张卡思出] 你的高潮阶段开始时，你可以支付费用。支付了的话，你从自己的休息室选择1张「“揺るぎ無い意志”なのは」，放置到这张卡原来的位置。",
    "all_cards": [
      {
        "id": "NA/W12-057",
        "rarity": "R"
      },
      {
        "id": "NA/W12-057SP",
        "rarity": "SP"
      }
    ],
    "trigger_soul_count": 1
  },
  "NA/W12-058": {
    "name": "なのはVSヴィータ",
    "product_name": "魔法少女リリカルなのはA's",
    "type": "角色卡",
    "level": 0,
    "power": 2500,
    "cost": 0,
    "trait": ["魔法", "人形"],
    "color": "红色",
    "soul": 1,
    "effect": "【自】你其他战斗中的《魔法》的角色倒置时，那个回合中，这张卡的战斗力+1500。",
    "all_cards": [
      {
        "id": "NA/W12-058",
        "rarity": "U"
      }
    ],
    "trigger_soul_count": 0
  },
  "NA/W12-059": {
    "name": "ヴィータ＆ザフィーラ",
    "product_name": "魔法少女リリカルなのはA's",
    "type": "角色卡",
    "level": 1,
    "power": 3000,
    "cost": 0,
    "trait": ["魔法", "使い魔"],
    "color": "红色",
    "soul": 1,
    "effect": "【永】你其他《魔法》的角色有3个以上的话，这张卡的战斗力+1000。<br/>【自】这张卡倒置时，这张卡的战斗对手的等级是1级以下的话，你可以将那个角色倒置。",
    "all_cards": [
      {
        "id": "NA/W12-059",
        "rarity": "U"
      }
    ],
    "trigger_soul_count": 0
  },
  "NA/W12-060": {
    "name": "ユーノ・スクライア",
    "product_name": "魔法少女リリカルなのはA's",
    "type": "角色卡",
    "level": 1,
    "power": 5500,
    "cost": 1,
    "trait": ["魔法", "動物"],
    "color": "红色",
    "soul": 1,
    "effect": "【永】记忆 你的思出区有卡的话，这张卡获得以下能力。『【自】你其他战斗中的角色倒置时，你选择自己的1个角色，那个回合中，战斗力+1000。』<br/>【自】再演 [手牌中1张角色卡放置到休息室] （这张卡从舞台放置到休息室时，你可以支付费用。支付了的话，你将这张卡横置放置到原来的位置）",
    "all_cards": [
      {
        "id": "NA/W12-060",
        "rarity": "U"
      }
    ],
    "trigger_soul_count": 0
  },
  "NA/W12-061": {
    "name": "後方支援 ユーノ",
    "product_name": "魔法少女リリカルなのはA's",
    "type": "角色卡",
    "level": 2,
    "power": 5500,
    "cost": 1,
    "trait": ["魔法", "動物"],
    "color": "红色",
    "soul": 1,
    "effect": "【永】你其他全部卡名含有「なのは」的角色，战斗力+1000。<br/>【自】[(2)] 对手使用事件卡时，你可以支付费用。支付了的话，给对手造成1点伤害。（发生伤害取消）",
    "all_cards": [
      {
        "id": "NA/W12-061",
        "rarity": "U"
      }
    ],
    "trigger_soul_count": 1
  },
  "NA/W12-062": {
    "name": "“八神家”ヴィータ",
    "product_name": "魔法少女リリカルなのはA's",
    "type": "角色卡",
    "level": 2,
    "power": 8500,
    "cost": 2,
    "trait": ["魔法", "人形"],
    "color": "红色",
    "soul": 2,
    "effect": "【永】记忆 你的思出区有3张以上的话，这张卡获得以下能力。<br/>【自】你其他战斗中的角色倒置时，那个回合中，这张卡的战斗力+2000。』",
    "all_cards": [
      {
        "id": "NA/W12-062",
        "rarity": "U"
      }
    ],
    "trigger_soul_count": 1
  },
  "NA/W12-063": {
    "name": "なのは＆ユーノ",
    "product_name": "魔法少女リリカルなのはA's",
    "type": "角色卡",
    "level": 0,
    "power": 1000,
    "cost": 0,
    "trait": ["魔法", "動物"],
    "color": "红色",
    "soul": 1,
    "effect": "【永】应援 你这张卡前的全部角色，战斗力+500。",
    "all_cards": [
      {
        "id": "NA/W12-063",
        "rarity": "C"
      }
    ],
    "trigger_soul_count": 0
  },
  "NA/W12-064": {
    "name": "“ヴォルケンリッター”ヴィータ",
    "product_name": "魔法少女リリカルなのはA's",
    "type": "角色卡",
    "level": 0,
    "power": 1500,
    "cost": 0,
    "trait": ["魔法", "武器"],
    "color": "红色",
    "soul": 1,
    "effect": "【永】这张卡不能侧面攻击。<br/>【自】[(2) 这张卡思出] 战斗中这张卡倒置时，你可以支付费用。支付了的话，你从自己的休息室选择1张《魔法》的角色卡返回手牌。",
    "all_cards": [
      {
        "id": "NA/W12-064",
        "rarity": "C"
      }
    ],
    "trigger_soul_count": 0
  },
  "NA/W12-065": {
    "name": "ちびっこ ヴィータ",
    "product_name": "魔法少女リリカルなのはA's",
    "type": "角色卡",
    "level": 0,
    "power": 3000,
    "cost": 0,
    "trait": ["魔法", "人形"],
    "color": "红色",
    "soul": 1,
    "effect": "",
    "all_cards": [
      {
        "id": "NA/W12-065",
        "rarity": "C"
      }
    ],
    "trigger_soul_count": 0
  },
  "NA/W12-066": {
    "name": "“高町なのは”リーゼアリア",
    "product_name": "魔法少女リリカルなのはA's",
    "type": "角色卡",
    "level": 1,
    "power": 3500,
    "cost": 0,
    "trait": ["双子", "使い魔"],
    "color": "红色",
    "soul": 1,
    "effect": "【自】[(1) 这张卡思出] 战斗中这张卡倒置时，你可以支付费用。支付了的话，你从对手的休息室选择1张卡放置到卡组顶。",
    "all_cards": [
      {
        "id": "NA/W12-066",
        "rarity": "C"
      }
    ],
    "trigger_soul_count": 0
  },
  "NA/W12-067": {
    "name": "祝福するなのは",
    "product_name": "魔法少女リリカルなのはA's",
    "type": "角色卡",
    "level": 1,
    "power": 5500,
    "cost": 0,
    "trait": ["魔法", "武器"],
    "color": "红色",
    "soul": 1,
    "effect": "",
    "all_cards": [
      {
        "id": "NA/W12-067",
        "rarity": "C"
      }
    ],
    "trigger_soul_count": 0
  },
  "NA/W12-068": {
    "name": "古代史学者 ユーノ",
    "product_name": "魔法少女リリカルなのはA's",
    "type": "角色卡",
    "level": 2,
    "power": 2500,
    "cost": 1,
    "trait": ["魔法", "本"],
    "color": "红色",
    "soul": 1,
    "effect": "【起】【反击】助太刀3000 等级2 [(1) 手牌中这张卡放置到休息室] （你选择自己1个被正面攻击的角色，那个回合中，战斗力+3000）",
    "all_cards": [
      {
        "id": "NA/W12-068",
        "rarity": "C"
      }
    ],
    "trigger_soul_count": 1
  },
  "NA/W12-069": {
    "name": "手加減なし！ なのは",
    "product_name": "魔法少女リリカルなのはA's",
    "type": "角色卡",
    "level": 2,
    "power": 8000,
    "cost": 1,
    "trait": ["魔法", "武器"],
    "color": "红色",
    "soul": 1,
    "effect": "【自】[手牌中1张高潮卡放置到休息室] 你的「エクセリオンバスター」放置到高潮区时，前列有这张卡的话，你可以支付费用。支付了的话，你选择这张卡正面的1个等级2以下的角色放置到卡组顶。",
    "all_cards": [
      {
        "id": "NA/W12-069",
        "rarity": "C"
      }
    ],
    "trigger_soul_count": 1
  },
  "NA/W12-070": {
    "name": "魔法訓練",
    "product_name": "魔法少女リリカルなのはA's",
    "type": "事件卡",
    "level": 3,
    "power": "-",
    "cost": 1,
    "trait": "-",
    "color": "红色",
    "soul": "-",
    "effect": "给对手造成1点伤害。你选择自己的1个角色，那个回合中，战斗力+3000。（发生伤害取消）",
    "all_cards": [
      {
        "id": "NA/W12-070",
        "rarity": "U"
      }
    ],
    "trigger_soul_count": 0
  },
  "NA/W12-071": {
    "name": "はやてからの贈り物",
    "product_name": "魔法少女リリカルなのはA's",
    "type": "事件卡",
    "level": 1,
    "power": "-",
    "cost": 1,
    "trait": "-",
    "color": "红色",
    "soul": "-",
    "effect": "你从自己的休息室选择至多2张卡名含有的「ヴィータ」的角色卡返回手牌，选择自己的1张手牌放置到休息室。",
    "all_cards": [
      {
        "id": "NA/W12-071",
        "rarity": "U"
      }
    ],
    "trigger_soul_count": 0
  },
  "NA/W12-072": {
    "name": "超長距離砲撃",
    "product_name": "魔法少女リリカルなのはA's",
    "type": "事件卡",
    "level": 2,
    "power": "-",
    "cost": 3,
    "trait": "-",
    "color": "红色",
    "soul": "-",
    "effect": "你选择对手1个费用1以下的角色放置到卡组顶。这张卡思出。",
    "all_cards": [
      {
        "id": "NA/W12-072",
        "rarity": "C"
      }
    ],
    "trigger_soul_count": 0
  },
  "NA/W12-073": {
    "name": "エクセリオンバスター",
    "product_name": "魔法少女リリカルなのはA's",
    "type": "高潮卡",
    "level": "-",
    "power": "-",
    "cost": "-",
    "trait": "-",
    "color": "红色",
    "soul": "-",
    "effect": "【永】你的全部角色战斗力+1000，灵魂值+1。<br/>（<img src=\"/effect-icons/salvage.webp\">：这张卡被触发时，你可以从自己的休息室选择1张角色卡返回手牌）",
    "all_cards": [
      {
        "id": "NA/W12-073",
        "rarity": "CR"
      },
      {
        "id": "NA/W12-073S",
        "rarity": "SR"
      }
    ],
    "trigger_soul_count": 0
  },
  "NA/W12-074": {
    "name": "I can be shot",
    "product_name": "魔法少女リリカルなのはA's",
    "type": "高潮卡",
    "level": "-",
    "power": "-",
    "cost": "-",
    "trait": "-",
    "color": "红色",
    "soul": "-",
    "effect": "【自】这张卡从手牌放置到高潮区时，你将自己卡组顶1张卡放置到库存区，自己的全部角色，那个回合中，灵魂值+1。",
    "all_cards": [
      {
        "id": "NA/W12-074",
        "rarity": "CC"
      }
    ],
    "trigger_soul_count": 2
  },
  "NA/W12-075": {
    "name": "轟天爆砕",
    "product_name": "魔法少女リリカルなのはA's",
    "type": "高潮卡",
    "level": "-",
    "power": "-",
    "cost": "-",
    "trait": "-",
    "color": "红色",
    "soul": "-",
    "effect": "【永】你的全部角色，灵魂值+2。",
    "all_cards": [
      {
        "id": "NA/W12-075",
        "rarity": "CC"
      }
    ],
    "trigger_soul_count": 2
  },
  "NA/W12-076": {
    "name": "“管制人格”闇の書の意志",
    "product_name": "魔法少女リリカルなのはA's",
    "type": "角色卡",
    "level": 1,
    "power": 5000,
    "cost": 1,
    "trait": ["魔法", "本"],
    "color": "蓝色",
    "soul": 1,
    "effect": "【自】[手牌中1张高潮卡放置到休息室] 这张卡攻击时，你可以支付费用。支付了的话，那个回合中，这张卡的战斗力+X。X是你休息室的高潮卡的数量×1000。",
    "all_cards": [
      {
        "id": "NA/W12-076",
        "rarity": "RR"
      },
      {
        "id": "NA/W12-076S",
        "rarity": "SR"
      }
    ],
    "trigger_soul_count": 1
  },
  "NA/W12-077": {
    "name": "マスター はやて",
    "product_name": "魔法少女リリカルなのはA's",
    "type": "角色卡",
    "level": 3,
    "power": 10000,
    "cost": 2,
    "trait": ["魔法", "本"],
    "color": "蓝色",
    "soul": 2,
    "effect": "【永】相手の高潮区有高潮卡的话，这张卡获得『【自】再演 [手牌中1张角色卡放置到休息室]』的能力。<br/>【自】这张卡从手牌放置到舞台时，你可以将自己时计区顶1张卡放置到休息室。",
    "all_cards": [
      {
        "id": "NA/W12-077",
        "rarity": "RR"
      },
      {
        "id": "NA/W12-077SP",
        "rarity": "SP"
      }
    ],
    "trigger_soul_count": 1
  },
  "NA/W12-078": {
    "name": "病室のはやて",
    "product_name": "魔法少女リリカルなのはA's",
    "type": "角色卡",
    "level": 0,
    "power": 2000,
    "cost": 0,
    "trait": ["本"],
    "color": "蓝色",
    "soul": 1,
    "effect": "【自】[这张卡放置到休息室] 这张卡被正面攻击时，你可以支付费用。支付了的话，你从自己的手牌中选择1张「“八神家”はやて」作为防御角色放置到这张卡的位置。",
    "all_cards": [
      {
        "id": "NA/W12-078",
        "rarity": "R"
      }
    ],
    "trigger_soul_count": 0
  },
  "NA/W12-079": {
    "name": "レティ・ロウラン",
    "product_name": "魔法少女リリカルなのはA's",
    "type": "角色卡",
    "level": 0,
    "power": 2500,
    "cost": 0,
    "trait": ["魔法", "メガネ"],
    "color": "蓝色",
    "soul": 1,
    "effect": "【自】这张卡攻击时，你选择自己其他1个《魔法》的角色，那个回合中，战斗力+1000。",
    "all_cards": [
      {
        "id": "NA/W12-079",
        "rarity": "R"
      }
    ],
    "trigger_soul_count": 0
  },
  "NA/W12-080": {
    "name": "湖の騎士 シャマル",
    "product_name": "魔法少女リリカルなのはA's",
    "type": "角色卡",
    "level": 1,
    "power": 3000,
    "cost": 0,
    "trait": ["魔法"],
    "color": "蓝色",
    "soul": 1,
    "effect": "【永】你其他全部卡名含有「シグナム」的角色，战斗力+500。<br/>【自】你的「癒しの力」放置到高潮区时，你将自己卡组顶3张卡放置到休息室。那些卡全部是《魔法》的角色卡的话，你将自己时计区顶1张卡放置到休息室。<br/>【起】[这张卡横置] 你选择自己1个卡名含有「ヴィータ」的角色，那个回合中，灵魂值+1。",
    "all_cards": [
      {
        "id": "NA/W12-080",
        "rarity": "R"
      },
      {
        "id": "NA/W12-080SP",
        "rarity": "SP"
      }
    ],
    "trigger_soul_count": 0
  },
  "NA/W12-081": {
    "name": "夜天の王 はやて",
    "product_name": "魔法少女リリカルなのはA's",
    "type": "角色卡",
    "level": 2,
    "power": 2500,
    "cost": 1,
    "trait": ["魔法", "本"],
    "color": "蓝色",
    "soul": 1,
    "effect": "【自】[(1)] 这张卡从手牌放置到舞台时，你可以支付费用。支付了的话，你从自己的卡组找至多1张《魔法》或《使い魔》的角色卡展示给对手后加入手牌。卡组洗切。<br/>【自】[(2) 这张卡思出] 你的「覚醒の時」放置到高潮区时，你可以支付费用。支付了的话，你从自己的卡组找至多1张「マスター はやて」，放置到这张卡原来的位置。卡组洗切。",
    "all_cards": [
      {
        "id": "NA/W12-081",
        "rarity": "R"
      }
    ],
    "trigger_soul_count": 1
  },
  "NA/W12-082": {
    "name": "“ヴォルケンリッター”シャマル",
    "product_name": "魔法少女リリカルなのはA's",
    "type": "角色卡",
    "level": 2,
    "power": 7500,
    "cost": 2,
    "trait": ["魔法"],
    "color": "蓝色",
    "soul": 2,
    "effect": "【自】再演 [手牌中1张角色卡放置到休息室] （这张卡从舞台放置到休息室时，你可以支付费用。支付了的话，你将这张卡横置放置到原来的位置）<br/>【起】[(2) 你的2个角色横置] 你看对手卡组顶至多2张卡选择至多2张卡放置到休息室。其余的卡返回卡组。卡组洗切。",
    "all_cards": [
      {
        "id": "NA/W12-082",
        "rarity": "R"
      }
    ],
    "trigger_soul_count": 1
  },
  "NA/W12-083": {
    "name": "はやての主治医 石田 幸恵",
    "product_name": "魔法少女リリカルなのはA's",
    "type": "角色卡",
    "level": 0,
    "power": 1000,
    "cost": 0,
    "trait": ["特徴なし"],
    "color": "蓝色",
    "soul": 1,
    "effect": "【永】对手的回合中，你其他全部角色，等级+1。<br/>【起】[(2) 这张卡横置] 你从自己的卡组找至多1张卡名含有「はやて」的角色卡展示给对手后加入手牌。卡组洗切。",
    "all_cards": [
      {
        "id": "NA/W12-083",
        "rarity": "U"
      }
    ],
    "trigger_soul_count": 0
  },
  "NA/W12-084": {
    "name": "“ヴォルケンリッター”ザフィーラ",
    "product_name": "魔法少女リリカルなのはA's",
    "type": "角色卡",
    "level": 0,
    "power": 1000,
    "cost": 0,
    "trait": ["使い魔", "動物"],
    "color": "蓝色",
    "soul": 1,
    "effect": "【永】你其他位于前列中央的角色，战斗力+1000。",
    "all_cards": [
      {
        "id": "NA/W12-084",
        "rarity": "U"
      }
    ],
    "trigger_soul_count": 0
  },
  "NA/W12-085": {
    "name": "盾の守護獣 ザフィーラ",
    "product_name": "魔法少女リリカルなのはA's",
    "type": "角色卡",
    "level": 1,
    "power": 4000,
    "cost": 0,
    "trait": ["使い魔", "動物"],
    "color": "蓝色",
    "soul": 1,
    "effect": "【永】记忆 对手的回合中，你的思出区有卡的话，你其他全部角色，战斗力+500。<br/>【自】再演 [手牌中1张角色卡放置到休息室] （这张卡从舞台放置到休息室时，你可以支付费用。支付了的话，你将这张卡横置放置到原来的位置）",
    "all_cards": [
      {
        "id": "NA/W12-085",
        "rarity": "U"
      }
    ],
    "trigger_soul_count": 0
  },
  "NA/W12-086": {
    "name": "中学三年生のはやて",
    "product_name": "魔法少女リリカルなのはA's",
    "type": "角色卡",
    "level": 1,
    "power": 2500,
    "cost": 1,
    "trait": ["魔法", "本"],
    "color": "蓝色",
    "soul": 1,
    "effect": "【永】应援 你这张卡前全部等级2以上的角色，战斗力+1000。<br/>【自】[(2)] 这张卡从手牌放置到舞台时，你可以支付费用。支付了的话，你从自己的卡组找至多1张卡名含有「八神」的角色卡展示给对手后加入手牌。卡组洗切。",
    "all_cards": [
      {
        "id": "NA/W12-086",
        "rarity": "U"
      }
    ],
    "trigger_soul_count": 1
  },
  "NA/W12-087": {
    "name": "“強く支えるもの”リインフォース",
    "product_name": "魔法少女リリカルなのはA's",
    "type": "角色卡",
    "level": 2,
    "power": 6000,
    "cost": 1,
    "trait": ["魔法", "本"],
    "color": "蓝色",
    "soul": 1,
    "effect": "【永】你其他全部《本》的角色，战斗力+1000。<br/>【自】[这张卡思出] 你的「愛する者の為に」放置到高潮区时，你可以支付费用。支付了的话，你从自己的时计区选择1张《本》的角色卡返回手牌。",
    "all_cards": [
      {
        "id": "NA/W12-087",
        "rarity": "U"
      }
    ],
    "trigger_soul_count": 1
  },
  "NA/W12-088": {
    "name": "歴戦の勇士 ギル・グレアム",
    "product_name": "魔法少女リリカルなのはA's",
    "type": "角色卡",
    "level": 0,
    "power": 500,
    "cost": 0,
    "trait": ["魔法"],
    "color": "蓝色",
    "soul": 1,
    "effect": "【自】[(2) 这张卡思出] 战斗中这张卡倒置时，你可以支付费用。支付了的话，你从自己的卡组找至多1张《使い魔》的角色卡展示给对手后加入手牌。卡组洗切。",
    "all_cards": [
      {
        "id": "NA/W12-088",
        "rarity": "C"
      }
    ],
    "trigger_soul_count": 0
  },
  "NA/W12-089": {
    "name": "世界で一番幸福な魔導書 リインフォース",
    "product_name": "魔法少女リリカルなのはA's",
    "type": "角色卡",
    "level": 0,
    "power": 1000,
    "cost": 0,
    "trait": ["魔法", "本"],
    "color": "蓝色",
    "soul": 1,
    "effect": "【自】绊／「“八神家”はやて」 [(1)] （这张卡被使用放置到舞台时，你可以支付费用。支付了的话，你从自己的休息室选择1张「“八神家”はやて」返回手牌）",
    "all_cards": [
      {
        "id": "NA/W12-089",
        "rarity": "C"
      }
    ],
    "trigger_soul_count": 0
  },
  "NA/W12-090": {
    "name": "“八神家”シャマル",
    "product_name": "魔法少女リリカルなのはA's",
    "type": "角色卡",
    "level": 0,
    "power": 3000,
    "cost": 0,
    "trait": ["魔法"],
    "color": "蓝色",
    "soul": 1,
    "effect": "",
    "all_cards": [
      {
        "id": "NA/W12-090",
        "rarity": "C"
      }
    ],
    "trigger_soul_count": 0
  },
  "NA/W12-091": {
    "name": "リーゼアリア＆リーゼロッテ",
    "product_name": "魔法少女リリカルなのはA's",
    "type": "角色卡",
    "level": 1,
    "power": 4500,
    "cost": 0,
    "trait": ["双子", "使い魔"],
    "color": "蓝色",
    "soul": 1,
    "effect": "【自】变身 [(2) 1张手牌放置到休息室，这张卡思出] 你的高潮阶段开始时，你可以支付费用。支付了的话，你从自己的休息室选择1张「仮面の戦士」，放置到这张卡原来的位置。",
    "all_cards": [
      {
        "id": "NA/W12-091",
        "rarity": "C"
      }
    ],
    "trigger_soul_count": 0
  },
  "NA/W12-092": {
    "name": "“八神家”はやて",
    "product_name": "魔法少女リリカルなのはA's",
    "type": "角色卡",
    "level": 1,
    "power": 5500,
    "cost": 0,
    "trait": ["本"],
    "color": "蓝色",
    "soul": 1,
    "effect": "",
    "all_cards": [
      {
        "id": "NA/W12-092",
        "rarity": "C"
      }
    ],
    "trigger_soul_count": 0
  },
  "NA/W12-093": {
    "name": "“八神家”ザフィーラ",
    "product_name": "魔法少女リリカルなのはA's",
    "type": "角色卡",
    "level": 2,
    "power": 1500,
    "cost": 1,
    "trait": ["使い魔", "動物"],
    "color": "蓝色",
    "soul": 1,
    "effect": "【永】你其他全部《魔法》的角色，战斗力+500。<br/>【起】【反击】助太刀3000 等级2 [(1) 手牌中这张卡放置到休息室] （你选择自己1个被正面攻击的角色，那个回合中，战斗力+3000）",
    "all_cards": [
      {
        "id": "NA/W12-093",
        "rarity": "C"
      }
    ],
    "trigger_soul_count": 0
  },
  "NA/W12-094": {
    "name": "仮面の戦士",
    "product_name": "魔法少女リリカルなのはA's",
    "type": "角色卡",
    "level": 2,
    "power": 8500,
    "cost": 1,
    "trait": ["双子", "仮面"],
    "color": "蓝色",
    "soul": 1,
    "effect": "",
    "all_cards": [
      {
        "id": "NA/W12-094",
        "rarity": "C"
      }
    ],
    "trigger_soul_count": 1
  },
  "NA/W12-095": {
    "name": "闇の書の呪い",
    "product_name": "魔法少女リリカルなのはA's",
    "type": "事件卡",
    "level": 2,
    "power": "-",
    "cost": 0,
    "trait": "-",
    "color": "蓝色",
    "soul": "-",
    "effect": "你没有《本》的角色的话，这张卡不能从手牌中使用。<br/>你选择对手1个等级3以下的角色。那个角色在下一个对手的准备阶段不会竖置。",
    "all_cards": [
      {
        "id": "NA/W12-095",
        "rarity": "U"
      }
    ],
    "trigger_soul_count": 0
  },
  "NA/W12-096": {
    "name": "旅の鏡",
    "product_name": "魔法少女リリカルなのはA's",
    "type": "事件卡",
    "level": 3,
    "power": "-",
    "cost": 5,
    "trait": "-",
    "color": "蓝色",
    "soul": "-",
    "effect": "你看对手卡组顶至多6张卡选择至多6张卡放置到休息室。其余的卡返回卡组。卡组洗切。",
    "all_cards": [
      {
        "id": "NA/W12-096",
        "rarity": "U"
      }
    ],
    "trigger_soul_count": 0
  },
  "NA/W12-097": {
    "name": "守護騎士プログラム",
    "product_name": "魔法少女リリカルなのはA's",
    "type": "事件卡",
    "level": 1,
    "power": "-",
    "cost": 2,
    "trait": "-",
    "color": "蓝色",
    "soul": "-",
    "effect": "这张卡思出。<br/>记忆 思出区有这张卡的话，你全部卡名含有「はやて」的角色卡，战斗力+500。",
    "all_cards": [
      {
        "id": "NA/W12-097",
        "rarity": "C"
      }
    ],
    "trigger_soul_count": 0
  },
  "NA/W12-098": {
    "name": "癒しの力",
    "product_name": "魔法少女リリカルなのはA's",
    "type": "高潮卡",
    "level": "-",
    "power": "-",
    "cost": "-",
    "trait": "-",
    "color": "蓝色",
    "soul": "-",
    "effect": "【永】你的全部角色战斗力+1000，灵魂值+1。<br/>（<img src=\"/effect-icons/draw.webp\">：这张卡被触发时，你可以抽1张卡）",
    "all_cards": [
      {
        "id": "NA/W12-098",
        "rarity": "CR"
      }
    ],
    "trigger_soul_count": 0
  },
  "NA/W12-099": {
    "name": "覚醒の時",
    "product_name": "魔法少女リリカルなのはA's",
    "type": "高潮卡",
    "level": "-",
    "power": "-",
    "cost": "-",
    "trait": "-",
    "color": "蓝色",
    "soul": "-",
    "effect": "【永】你的全部角色，灵魂值+2。",
    "all_cards": [
      {
        "id": "NA/W12-099",
        "rarity": "CC"
      },
      {
        "id": "NA/W12-099S",
        "rarity": "SR"
      }
    ],
    "trigger_soul_count": 2
  },
  "NA/W12-100": {
    "name": "愛する者の為に",
    "product_name": "魔法少女リリカルなのはA's",
    "type": "高潮卡",
    "level": "-",
    "power": "-",
    "cost": "-",
    "trait": "-",
    "color": "蓝色",
    "soul": "-",
    "effect": "【自】这张卡从手牌放置到高潮区时，你抽1张卡，选择自己的1个角色，那个回合中，战斗力+2000，灵魂值+1。",
    "all_cards": [
      {
        "id": "NA/W12-100",
        "rarity": "CC"
      }
    ],
    "trigger_soul_count": 2
  }
}
